{"mdsDat": {"x": [0.005204549192848297, 0.050253500299988166, 0.11822411207548507, -0.05313355136091816, -0.12054861020740339], "y": [0.14472403003526588, 0.008757004046204987, -0.07878676151891194, -0.013099287878287104, -0.06159498468427194], "topics": [1, 2, 3, 4, 5], "cluster": [1, 1, 1, 1, 1], "Freq": [16.532731921108663, 20.160450429857438, 33.69447107489092, 9.653140143919464, 19.959206430223514]}, "tinfo": {"Term": ["hydrogen", "climate", "neutrality", "emission", "Destinus", "mission", "Kosovo", "hostage", "Ukrainian", "compensation", "carbon", "aircraft", "democracy", "KFOR", "ICRC", "Nina Weil", "Gaza", "NATO", "party", "time", "speed", "Israeli", "company", "labour", "development", "peace", "film", "Jews", "Dea Gjinovci", "fuel", "compensation", "c", "credit", "lift", "Felix Wertli", "agency", "2030", "ski", "oil", "South Pole", "mechanism", "climate", "Patrick Hofstetter", "resort", "method", "emission", "the United Nations Environment Programme", "\u00b0", "the Human Rights Council", "Erika Lennon", "Wertli", "planting", "atmosphere", "tree", "certification", "justice", "the United Nations", "reduction", "United Nations", "reporter", "carbon", "effort", "strategy", "SWI", "Dubai", "agreement", "target", "conference", "analysis", "newsletter", "confidence", "country", "objective", "crisis", "report", "Ukraine", "energy", "project", "year", "world", "war", "Switzerland", "company", "Swiss", "member", "fuel", "development", "article", "labour", "Dea Gjinovci", "MSC", "shipping", "freight", "gold", "Hamburg", "port", "film", "container", "Ukrainians", "Ukrainian", "Vietnamese", "Larisa Verbitskaya", "trauma", "Polish", "record", "help", "north", "Jan Tiedemann", "subject", "gender", "the United Kingdom", "Berisha", "datum", "filmmaker", "HHLA", "Darya Kaysina", "apartment", "Charkiv", "family", "ship", "Spanish", "English", "woman", "business", "violence", "shortage", "Russian", "bar", "staff", "figure", "recruitment", "immigration", "rate", "Switzerland", "year", "job", "article", "Geneva", "company", "market", "work", "Swiss", "world", "people", "country", "war", "situation", "Kosovo", "time", "KFOR", "NATO", "Nato", "Serbia", "out", "KLA", "burn", "Swisscoy", "Thaci", "peace", "Baer", "referendum", "solidarity", "SWISSCOY", "Rietiker", "Pro Switzerland", "accession", "neutrality", "mission", "Silja H\u00e4usermann", "Jensen", "pillar", "electorate", "the Ukraine war", "Belgrade", "Hashim Thaci", "speech", "cooperation", "Parliament", "stress", "decision", "EU", "Kosovo", "government", "the Federal Council", "troop", "party", "minister", "Switzerland", "freedom", "army", "law", "Swiss", "state", "security", "debate", "democracy", "country", "policy", "war", "time", "year", "people", "member", "right", "hostage", "Gaza", "Israeli", "Fabrizio Carboni", "the Gaza Strip", "tax", "release", "electricity", "Carboni", "truce", "store", "intermediary", "battlefield", "icrc", "prisoner", "Monika B\u00fctler", "World War II", "FSCI", "reader", "economist", "parttime", "Jew", "rest", "promise", "four-day", "October 7", "ability", "The Geneva Conventions", "Al-Shifa Hospital", "Eli Cohen", "ICRC", "Jews", "Hamas", "Jewish", "stereotype", "middle", "Palestinian", "liberation", "percent", "past", "hydrogen", "Israel", "transition", "visit", "hospital", "time", "part", "development", "people", "conflict", "Switzerland", "place", "party", "Swiss", "day", "fuel", "energy", "year", "war", "operation", "work", "Destinus", "Nina Weil", "aircraft", "Mikhail Kokorich", "salt", "passenger", "Urs Bieri", "speed", "Martina L\u00f6fqvist", "aviation", "SSR", "Auschwitz", "aerospace", "entrepreneur", "Gaspard Stockalper", "Bieri", "selection", "dance", "bracelet", "meter", "propulsion", "combustion", "footprint", "investor", "sound", "mistake", "corruption", "Payerne", "prototype", "London", "engine", "residence", "Valais", "hydrogen", "technology", "plane", "opinion", "politician", "husband", "dialogue", "class", "flight", "challenge", "system", "democracy", "development", "people", "life", "company", "Swiss", "fuel", "Switzerland", "country", "franc", "time", "year", "power", "today", "standard", "Europe", "Articles"], "Freq": [57.0, 40.0, 75.0, 32.0, 27.0, 57.0, 53.0, 13.0, 25.0, 17.0, 23.0, 21.0, 44.0, 26.0, 14.0, 16.0, 10.0, 25.0, 48.0, 63.0, 17.0, 9.0, 45.0, 14.0, 56.0, 26.0, 15.0, 11.0, 13.0, 26.0, 17.01545707168168, 9.346534873444485, 7.819331150587061, 7.030633996568714, 6.286616202651221, 6.2852001039158125, 6.285623488537725, 6.266435350672937, 5.5196971058515025, 4.753224031986814, 4.752747664078883, 35.37897077953438, 3.9866030865875106, 3.978133949150541, 3.9782307640640844, 27.197257072558813, 3.219841494647139, 3.2199241004067045, 3.219232668524161, 3.218939333786112, 3.2190173637164303, 3.2149894298134183, 3.2147006709046164, 3.214182398034106, 3.2017720266167005, 3.199500729478326, 7.05991304208888, 7.05399240070941, 6.908574955568742, 3.1133790472192424, 18.49590256296137, 7.8025523072374146, 4.750851344105651, 10.153882625807647, 6.13671107318477, 12.426883899326555, 4.758129802605909, 6.104030019035967, 6.909238209976449, 5.890645614590521, 9.142577158914236, 38.2378217332166, 6.29114193860969, 8.506282573798766, 9.376246936911294, 11.93811501246906, 10.096041254127277, 9.357625720206906, 17.7891093808019, 12.146751632820996, 12.220580470224387, 21.320593747148624, 10.88591319209653, 15.882764969854497, 8.847388005854636, 8.229576880899907, 8.685163780722604, 7.036921667620423, 13.823525543099782, 13.012274557982966, 10.596339650753707, 8.992921481993756, 7.3879151011386135, 6.588577468805358, 6.586782507206652, 6.585278874453809, 13.814523716705223, 4.98001816821508, 4.977739812180597, 22.662172542582226, 4.1773373024329254, 4.1755940282100985, 4.174244282871804, 3.3748708217893593, 3.3746925590782313, 3.374758343011168, 3.3746279498583824, 3.37441885092869, 3.374268193975134, 3.3741410312833406, 3.373935456492913, 3.373859393820455, 3.373677606970062, 3.373097298704512, 3.372644740487299, 3.3723992254518738, 3.3720949747620406, 3.3721357960418543, 16.17860796293625, 5.783472582565788, 10.24746630955387, 13.1382789826712, 13.016265058343441, 8.796409603041162, 9.007007466633864, 8.85649617750047, 15.440110483508358, 4.984802187266606, 8.204599721644707, 5.934749784632662, 5.479191350192446, 4.9770226498402765, 7.395127839499907, 72.20925171747149, 32.23807887389765, 9.000866066608971, 14.611766248245749, 9.8146156664643, 16.52064917281536, 9.588204402635352, 14.498715384780638, 26.5502590666048, 13.759392082051768, 16.341801454569406, 21.178063521264548, 11.491226683608144, 8.303495879754049, 9.058628471223358, 8.427886836015697, 25.753030802422984, 24.865957485484476, 19.59077460149461, 18.678087863195614, 16.094778183715988, 16.01769741341679, 13.44013141508005, 13.407291027290931, 13.391328286039098, 24.877876777304152, 7.2509738574537295, 7.249956859732992, 7.242452574910433, 7.234571824232755, 6.355049911702323, 6.351628342633184, 6.347858775791844, 68.09369101990663, 51.79891768209688, 5.4881800987121565, 5.4827554564295395, 5.474404982383741, 5.471352516734484, 5.464155981704831, 5.461534463931445, 5.460961666470007, 6.232278849980375, 8.539554144238574, 10.789505517741542, 4.59692442773002, 9.895715696550832, 17.827807089281443, 44.30270208855693, 38.25225281079556, 14.804598775997666, 17.834898586901716, 34.14794058067952, 10.037975615174117, 150.8018042053492, 14.591140182000526, 16.056709485250572, 22.374177600871153, 80.765074250545, 22.694698764768592, 18.852147612094523, 19.511329016997287, 25.285985397412993, 54.7328343808264, 16.568981839092398, 27.448986410767066, 24.253088743196493, 28.779472697262847, 21.94040843981631, 16.71428293429758, 16.507486853360902, 12.906805340692008, 9.553152598234558, 8.876201232233843, 5.509657215386809, 4.16988910006905, 3.500924260751773, 3.4968620947043196, 6.81094584128954, 2.8256091230855973, 2.825538814202195, 2.8252848585153454, 2.8237369381383597, 2.8232996168835975, 5.516999712698281, 6.862635244953731, 1.481103032733122, 1.4808667948848904, 1.4808039387431287, 1.4807218179673147, 1.4808573734945143, 1.4807824242248075, 1.4801548471315582, 1.4799404050371812, 1.4799252183183662, 1.4798885170812301, 1.479814552135891, 1.479803021479013, 1.4796903866478024, 1.4795925166821065, 1.4795123645550279, 9.548655079581078, 7.5391338217453345, 5.513799252325807, 4.174708914644047, 2.8266210085355232, 4.172058832210846, 4.843620600445472, 3.498561038562854, 3.5022890967963787, 4.838682104475292, 18.069366160266735, 4.8444907431864594, 3.4748101352784797, 2.825779551818964, 4.169754950719518, 12.93012201631249, 7.522540925262385, 9.561652661002366, 10.268730539834378, 5.527296870525853, 13.254244843855096, 5.528267133116805, 6.874192337971873, 9.435628206036695, 4.847964002026534, 5.172596990827107, 4.834188523119282, 4.657241593789572, 4.208795786259631, 4.195775705995653, 4.193947675027193, 26.694625912529506, 15.460167195745408, 20.30927390258273, 9.004976074176012, 8.131040216758443, 6.595147880192332, 6.590266242414159, 15.452961328521214, 5.791918722671956, 5.788627469566005, 4.993689827600002, 4.993183928270995, 4.986942177239321, 4.981283664169708, 4.926291244119727, 4.1887842243721245, 3.3840196333135393, 3.3827019690841955, 3.3821966512486705, 3.3793307606245224, 3.3790908945633555, 3.37901704489119, 3.37877601584306, 3.3785745283516797, 3.3784474720259463, 3.3784704410184703, 3.3783858337168953, 3.37816108648625, 3.3777206051739257, 3.376774806026076, 10.618732713904537, 6.593353391308063, 11.295717892085465, 37.25500342957987, 7.418276907640598, 7.400732086313256, 15.471222549817906, 9.001138217197342, 4.99111381147644, 6.608004119577397, 6.602864298693387, 8.204049049349356, 9.843526308756754, 13.825100564396074, 18.28588359823578, 20.944025209193832, 21.87496370962733, 9.010361285309266, 16.040029006652773, 30.98503833417728, 11.447209736903233, 41.996915302042034, 25.9715969174872, 9.006714158192564, 13.58916888812577, 15.773050230411988, 8.90638850631574, 8.907760249438873, 8.93873698869808, 8.227943198002471, 8.147542420273245], "Total": [57.0, 40.0, 75.0, 32.0, 27.0, 57.0, 53.0, 13.0, 25.0, 17.0, 23.0, 21.0, 44.0, 26.0, 14.0, 16.0, 10.0, 25.0, 48.0, 63.0, 17.0, 9.0, 45.0, 14.0, 56.0, 26.0, 15.0, 11.0, 13.0, 26.0, 17.715599963705102, 10.021641943770131, 8.48262204649097, 7.709091261497942, 6.943865113330616, 6.943221933363708, 6.944082694569077, 6.9397620392786195, 6.1744123741826185, 5.405291833421435, 5.405109063375064, 40.37299625357266, 4.635711768827262, 4.633800712881777, 4.63729096553211, 32.460014739840325, 3.8662767125736743, 3.86639249630995, 3.866040360002541, 3.866339457385302, 3.8665175841696677, 3.8676212411962307, 3.8676617496002557, 3.867770399587029, 3.866914215121423, 3.8670953841519604, 8.59752583422518, 8.598573309790446, 8.579629538846426, 3.8803400866633972, 23.291980688381898, 10.257458662136898, 6.08031059231521, 15.152377979199501, 8.541473841168498, 20.876661454548408, 6.289633835378916, 8.61392390802295, 10.27958871334241, 8.59960489695945, 16.565804370673177, 143.59395956060874, 10.17628599291189, 17.172834070368683, 20.665372238218854, 32.1557064861323, 23.767372298717405, 23.2510364930088, 99.23695277616396, 47.77933270056833, 59.13605724703213, 299.5828098158665, 45.6161238370033, 163.61876482721826, 32.49997824256677, 26.139175471556044, 56.014357682556366, 33.555433588012484, 14.489651647281079, 13.683723343442162, 11.264791768444809, 9.653541852652614, 8.041990177876707, 7.235796162452412, 7.23586367168066, 7.2356174678006235, 15.374564787851348, 5.624073075954859, 5.6239538415916215, 25.66062099281714, 4.8184301522711745, 4.818007344797851, 4.818264915291838, 4.012261141619192, 4.0124058429480005, 4.01250091393971, 4.012360412534612, 4.012321915695553, 4.012400656669093, 4.012449573844932, 4.01232972714362, 4.01235802130638, 4.012410712825954, 4.012368559749312, 4.0122472376328915, 4.012105756390831, 4.011963000187606, 4.012202795878528, 19.91170051521652, 7.107286487859925, 13.690166426344787, 18.49314776818351, 18.55028350950266, 12.077320817643328, 12.77708498172036, 12.566630222813226, 24.608775442361036, 6.392775370597735, 11.972262330334972, 8.045718396773264, 7.31538072639155, 6.5095952225963805, 10.745632361591097, 299.5828098158665, 99.23695277616396, 15.567947084485478, 33.555433588012484, 18.54803999659807, 45.6161238370033, 18.70932530933774, 42.177350989039674, 163.61876482721826, 47.77933270056833, 73.27561042319593, 143.59395956060874, 59.13605724703213, 26.178210315848048, 53.95370530236025, 63.22006167226372, 26.480992934097536, 25.593968428373003, 20.279812052517187, 19.391342487279765, 16.741509816591154, 16.73139605482235, 14.082625395651391, 14.077595302832401, 14.0759250315264, 26.400781505499452, 7.878662486641737, 7.878134496308186, 7.877163595768008, 7.876349167967669, 6.990644523327708, 6.990241202440513, 6.989693386951063, 75.35816326578436, 57.569409126940805, 6.106652168241466, 6.1061009235716694, 6.104861755253218, 6.104676474485936, 6.103161368226113, 6.103403592157944, 6.103101226810919, 6.9744861825511215, 9.607211396108832, 12.228662511649903, 5.219691444934612, 11.341498031560608, 20.795810917330034, 53.95370530236025, 50.44595410771293, 18.065148153951675, 22.549776863213577, 48.35043772653191, 12.129520389567073, 299.5828098158665, 19.023785550367467, 21.597814233494553, 32.95287512237514, 163.61876482721826, 33.69530683629206, 26.88173158938605, 30.562203618937758, 44.98524445525091, 143.59395956060874, 25.9089087246123, 59.13605724703213, 63.22006167226372, 99.23695277616396, 73.27561042319593, 32.49997824256677, 35.242545851521655, 13.63274601877168, 10.251446235976237, 9.576260214837319, 6.1975126894565955, 4.844494281509889, 4.168109185667394, 4.168806151225952, 8.362911709290042, 3.492503628532384, 3.4925283571866914, 3.492558360254885, 3.492899126463771, 3.493000004710927, 7.770830311775275, 9.85582810781178, 2.140674337550313, 2.1404941673401945, 2.140508851961805, 2.1404969812800867, 2.140709695007892, 2.140720093255223, 2.1406115423219574, 2.140701656840489, 2.140757391063155, 2.140785230145494, 2.140787410881114, 2.1407936553961586, 2.1408110385472274, 2.1408352786788365, 2.140862909439304, 14.245020097278497, 11.455052342282935, 8.614191072292376, 6.459443059200175, 4.297715613990525, 6.615376918295659, 7.937878096854293, 5.784620581856179, 5.9391738557983755, 9.51330158775297, 57.02096797603851, 10.36201336259742, 6.6752663722902295, 5.069535057970754, 8.874175719968518, 63.22006167226372, 32.48596409381061, 56.014357682556366, 73.27561042319593, 23.14301931744958, 299.5828098158665, 23.99867180154823, 48.35043772653191, 163.61876482721826, 18.837039499913224, 26.139175471556044, 23.767372298717405, 99.23695277616396, 59.13605724703213, 13.036132951416928, 42.177350989039674, 27.457461561955423, 16.143602131079824, 21.677350650118516, 9.678634512530595, 8.870622418588482, 7.2539774650169155, 7.254100843886828, 17.028615705209546, 6.445803321801834, 6.4458904216479365, 5.638050018746926, 5.637816690467358, 5.63772871405522, 5.637557236071507, 5.637588374283081, 4.8295835215199485, 4.021670928630056, 4.0213525265232635, 4.021398241618112, 4.0212962785800626, 4.021302734640701, 4.021390597253292, 4.02131593938109, 4.021415659428015, 4.0212801953723165, 4.021499205477961, 4.021543747882375, 4.021357839537186, 4.021295001920581, 4.021266216338599, 12.905639215884204, 8.059723205658562, 14.409272653223777, 57.02096797603851, 9.62767427458831, 9.746556691294776, 23.001988544657245, 13.221100626656, 6.442922308866738, 9.411987000887493, 9.411028118675615, 12.875343064055222, 16.655029445880736, 27.86216874909945, 44.98524445525091, 56.014357682556366, 73.27561042319593, 16.11664515157653, 45.6161238370033, 163.61876482721826, 26.139175471556044, 299.5828098158665, 143.59395956060874, 17.787952775246538, 63.22006167226372, 99.23695277616396, 22.494028688199805, 34.9898053517678, 38.77268762912535, 31.083216032995562, 34.744259283472374], "Category": ["Default", "Default", "Default", "Default", "Default", "Default", "Default", "Default", "Default", "Default", "Default", "Default", "Default", "Default", "Default", "Default", "Default", "Default", "Default", "Default", "Default", "Default", "Default", "Default", "Default", "Default", "Default", "Default", "Default", "Default", "Topic1", "Topic1", "Topic1", "Topic1", "Topic1", "Topic1", "Topic1", "Topic1", "Topic1", "Topic1", "Topic1", "Topic1", "Topic1", "Topic1", "Topic1", "Topic1", "Topic1", "Topic1", "Topic1", "Topic1", "Topic1", "Topic1", "Topic1", "Topic1", "Topic1", "Topic1", "Topic1", "Topic1", "Topic1", "Topic1", "Topic1", "Topic1", "Topic1", "Topic1", "Topic1", "Topic1", "Topic1", "Topic1", "Topic1", "Topic1", "Topic1", "Topic1", "Topic1", "Topic1", "Topic1", "Topic1", "Topic1", "Topic1", "Topic1", "Topic1", "Topic1", "Topic1", "Topic1", "Topic1", "Topic1", "Topic1", "Topic1", "Topic1", "Topic2", "Topic2", "Topic2", "Topic2", "Topic2", "Topic2", "Topic2", "Topic2", "Topic2", "Topic2", "Topic2", "Topic2", "Topic2", "Topic2", "Topic2", "Topic2", "Topic2", "Topic2", "Topic2", "Topic2", "Topic2", "Topic2", "Topic2", "Topic2", "Topic2", "Topic2", "Topic2", "Topic2", "Topic2", "Topic2", "Topic2", "Topic2", "Topic2", "Topic2", "Topic2", "Topic2", "Topic2", "Topic2", "Topic2", "Topic2", "Topic2", "Topic2", "Topic2", "Topic2", "Topic2", "Topic2", "Topic2", "Topic2", "Topic2", "Topic2", "Topic2", "Topic2", "Topic2", "Topic2", "Topic2", "Topic2", "Topic2", "Topic2", "Topic2", "Topic2", "Topic2", "Topic3", "Topic3", "Topic3", "Topic3", "Topic3", "Topic3", "Topic3", "Topic3", "Topic3", "Topic3", "Topic3", "Topic3", "Topic3", "Topic3", "Topic3", "Topic3", "Topic3", "Topic3", "Topic3", "Topic3", "Topic3", "Topic3", "Topic3", "Topic3", "Topic3", "Topic3", "Topic3", "Topic3", "Topic3", "Topic3", "Topic3", "Topic3", "Topic3", "Topic3", "Topic3", "Topic3", "Topic3", "Topic3", "Topic3", "Topic3", "Topic3", "Topic3", "Topic3", "Topic3", "Topic3", "Topic3", "Topic3", "Topic3", "Topic3", "Topic3", "Topic3", "Topic3", "Topic3", "Topic3", "Topic3", "Topic4", "Topic4", "Topic4", "Topic4", "Topic4", "Topic4", "Topic4", "Topic4", "Topic4", "Topic4", "Topic4", "Topic4", "Topic4", "Topic4", "Topic4", "Topic4", "Topic4", "Topic4", "Topic4", "Topic4", "Topic4", "Topic4", "Topic4", "Topic4", "Topic4", "Topic4", "Topic4", "Topic4", "Topic4", "Topic4", "Topic4", "Topic4", "Topic4", "Topic4", "Topic4", "Topic4", "Topic4", "Topic4", "Topic4", "Topic4", "Topic4", "Topic4", "Topic4", "Topic4", "Topic4", "Topic4", "Topic4", "Topic4", "Topic4", "Topic4", "Topic4", "Topic4", "Topic4", "Topic4", "Topic4", "Topic4", "Topic4", "Topic4", "Topic4", "Topic4", "Topic4", "Topic5", "Topic5", "Topic5", "Topic5", "Topic5", "Topic5", "Topic5", "Topic5", "Topic5", "Topic5", "Topic5", "Topic5", "Topic5", "Topic5", "Topic5", "Topic5", "Topic5", "Topic5", "Topic5", "Topic5", "Topic5", "Topic5", "Topic5", "Topic5", "Topic5", "Topic5", "Topic5", "Topic5", "Topic5", "Topic5", "Topic5", "Topic5", "Topic5", "Topic5", "Topic5", "Topic5", "Topic5", "Topic5", "Topic5", "Topic5", "Topic5", "Topic5", "Topic5", "Topic5", "Topic5", "Topic5", "Topic5", "Topic5", "Topic5", "Topic5", "Topic5", "Topic5", "Topic5", "Topic5", "Topic5", "Topic5", "Topic5", "Topic5", "Topic5", "Topic5", "Topic5"], "logprob": [30.0, 29.0, 28.0, 27.0, 26.0, 25.0, 24.0, 23.0, 22.0, 21.0, 20.0, 19.0, 18.0, 17.0, 16.0, 15.0, 14.0, 13.0, 12.0, 11.0, 10.0, 9.0, 8.0, 7.0, 6.0, 5.0, 4.0, 3.0, 2.0, 1.0, -4.8006, -5.3997, -5.5781, -5.6844, -5.7963, -5.7965, -5.7964, -5.7995, -5.9264, -6.0759, -6.076, -4.0686, -6.2518, -6.2539, -6.2539, -4.3316, -6.4654, -6.4653, -6.4656, -6.4656, -6.4656, -6.4669, -6.467, -6.4671, -6.471, -6.4717, -5.6803, -5.6811, -5.7019, -6.499, -4.7171, -5.5802, -6.0764, -5.3168, -5.8204, -5.1148, -6.0748, -5.8257, -5.7018, -5.8613, -5.4218, -3.9909, -5.7956, -5.4939, -5.3965, -5.155, -5.3226, -5.3985, -4.7561, -5.1376, -5.1316, -4.575, -5.2472, -4.8695, -5.4546, -5.527, -5.4731, -5.6835, -5.2067, -5.2672, -5.4726, -5.6366, -5.8332, -5.9477, -5.948, -5.9482, -5.2074, -6.2276, -6.2281, -4.7124, -6.4034, -6.4038, -6.4041, -6.6167, -6.6168, -6.6168, -6.6168, -6.6169, -6.6169, -6.6169, -6.617, -6.617, -6.6171, -6.6172, -6.6174, -6.6175, -6.6175, -6.6175, -5.0494, -6.0781, -5.506, -5.2575, -5.2669, -5.6587, -5.6351, -5.6519, -5.0961, -6.2267, -5.7284, -6.0523, -6.1321, -6.2282, -5.8323, -3.5535, -4.3599, -5.6358, -5.1512, -5.5492, -5.0285, -5.5725, -5.159, -4.554, -5.2114, -5.0393, -4.7801, -5.3915, -5.7164, -5.6294, -5.7015, -5.0981, -5.1332, -5.3716, -5.4193, -5.5682, -5.573, -5.7484, -5.7509, -5.7521, -5.1327, -6.3656, -6.3657, -6.3667, -6.3678, -6.4974, -6.498, -6.4986, -4.1258, -4.3993, -6.6441, -6.6451, -6.6466, -6.6472, -6.6485, -6.649, -6.6491, -6.5169, -6.202, -5.9681, -6.8213, -6.0546, -5.4659, -4.5556, -4.7025, -5.6517, -5.4655, -4.816, -6.0403, -3.3307, -5.6663, -5.5706, -5.2388, -3.9551, -5.2246, -5.4101, -5.3757, -5.1164, -4.3442, -5.5392, -5.0344, -5.1581, -4.987, -5.2584, -5.5304, -5.5429, -4.5389, -4.8398, -4.9133, -5.3901, -5.6687, -5.8436, -5.8448, -5.1781, -6.0579, -6.0579, -6.058, -6.0586, -6.0587, -5.3888, -5.1705, -6.7038, -6.704, -6.7041, -6.7041, -6.704, -6.7041, -6.7045, -6.7046, -6.7046, -6.7047, -6.7047, -6.7047, -6.7048, -6.7049, -6.7049, -4.8402, -5.0765, -5.3894, -5.6676, -6.0576, -5.6682, -5.519, -5.8443, -5.8432, -5.52, -4.2024, -5.5188, -5.8511, -6.0579, -5.6688, -4.5371, -5.0787, -4.8389, -4.7675, -5.3869, -4.5123, -5.3868, -5.1689, -4.8521, -5.5181, -5.4533, -5.5209, -5.5582, -5.6595, -5.6626, -5.663, -4.5386, -5.0848, -4.812, -5.6253, -5.7274, -5.9367, -5.9374, -5.0852, -6.0666, -6.0671, -6.2149, -6.215, -6.2162, -6.2174, -6.2285, -6.3906, -6.604, -6.6044, -6.6045, -6.6054, -6.6054, -6.6055, -6.6055, -6.6056, -6.6056, -6.6056, -6.6056, -6.6057, -6.6058, -6.6061, -5.4604, -5.937, -5.3986, -4.2053, -5.8191, -5.8215, -5.0841, -5.6257, -6.2154, -5.9348, -5.9355, -5.7184, -5.5362, -5.1966, -4.9169, -4.7812, -4.7377, -5.6247, -5.048, -4.3895, -5.3853, -4.0854, -4.566, -5.6251, -5.2138, -5.0647, -5.6363, -5.6361, -5.6326, -5.7155, -5.7253], "loglift": [30.0, 29.0, 28.0, 27.0, 26.0, 25.0, 24.0, 23.0, 22.0, 21.0, 20.0, 19.0, 18.0, 17.0, 16.0, 15.0, 14.0, 13.0, 12.0, 11.0, 10.0, 9.0, 8.0, 7.0, 6.0, 5.0, 4.0, 3.0, 2.0, 1.0, 1.7595, 1.7301, 1.7184, 1.7077, 1.7004, 1.7003, 1.7002, 1.6978, 1.6877, 1.6713, 1.6712, 1.6678, 1.649, 1.6473, 1.6465, 1.6229, 1.6169, 1.6169, 1.6167, 1.6166, 1.6165, 1.615, 1.6149, 1.6147, 1.6111, 1.6103, 1.6028, 1.6018, 1.5832, 1.5796, 1.5693, 1.5263, 1.5531, 1.3995, 1.4692, 1.2811, 1.5208, 1.4554, 1.4025, 1.4215, 1.2054, 0.4767, 1.3189, 1.0973, 1.0095, 0.809, 0.9437, 0.8897, 0.0809, 0.4303, 0.2231, -0.8429, 0.367, -0.5325, 0.4987, 0.6441, -0.0642, 0.2378, 1.5544, 1.5511, 1.5403, 1.5306, 1.5166, 1.5077, 1.5075, 1.5073, 1.4945, 1.4798, 1.4794, 1.4772, 1.4587, 1.4583, 1.458, 1.4284, 1.4284, 1.4284, 1.4284, 1.4283, 1.4282, 1.4282, 1.4282, 1.4281, 1.4281, 1.4279, 1.4278, 1.4278, 1.4277, 1.4277, 1.3938, 1.3953, 1.3118, 1.2596, 1.2472, 1.2845, 1.2518, 1.2516, 1.1353, 1.3527, 1.2235, 1.2971, 1.3124, 1.333, 1.2278, 0.1786, 0.4771, 1.0536, 0.7701, 0.965, 0.5858, 0.933, 0.5336, -0.2171, 0.3566, 0.1009, -0.3126, -0.0368, 0.4532, -0.183, -0.4136, 1.06, 1.059, 1.0533, 1.0504, 1.0484, 1.0442, 1.0411, 1.0391, 1.038, 1.0284, 1.0048, 1.0047, 1.0038, 1.0028, 0.9925, 0.992, 0.9915, 0.9865, 0.9822, 0.9811, 0.9802, 0.9788, 0.9783, 0.9772, 0.9767, 0.9767, 0.9753, 0.97, 0.9626, 0.9608, 0.9515, 0.9338, 0.8908, 0.8111, 0.8888, 0.8533, 0.7401, 0.8986, 0.4014, 0.8226, 0.7914, 0.7007, 0.3818, 0.6926, 0.733, 0.6391, 0.5118, 0.1233, 0.6408, 0.3203, 0.1298, -0.15, -0.1181, 0.4229, 0.3294, 2.2832, 2.2673, 2.262, 2.2202, 2.1879, 2.1635, 2.1621, 2.1326, 2.126, 2.126, 2.1259, 2.1252, 2.125, 1.9953, 1.9759, 1.9696, 1.9695, 1.9694, 1.9694, 1.9694, 1.9693, 1.9689, 1.9688, 1.9687, 1.9687, 1.9686, 1.9686, 1.9685, 1.9685, 1.9684, 1.9379, 1.9196, 1.8917, 1.9014, 1.9189, 1.8769, 1.8439, 1.835, 1.8097, 1.6618, 1.1887, 1.5776, 1.685, 1.7534, 1.5826, 0.7508, 0.875, 0.57, 0.3728, 0.9059, -0.7802, 0.8698, 0.3872, -0.5152, 0.9806, 0.7178, 0.7453, -0.7212, -0.3048, 1.2042, 0.0296, 1.5833, 1.5682, 1.5463, 1.5393, 1.5244, 1.5163, 1.5155, 1.5144, 1.5045, 1.5039, 1.4901, 1.4901, 1.4888, 1.4877, 1.4766, 1.4691, 1.4388, 1.4385, 1.4384, 1.4376, 1.4375, 1.4374, 1.4374, 1.4373, 1.4373, 1.4372, 1.4372, 1.4372, 1.4371, 1.4368, 1.4164, 1.4107, 1.368, 1.1858, 1.3508, 1.3361, 1.2149, 1.227, 1.3562, 1.2578, 1.2571, 1.1608, 1.0856, 0.9107, 0.7113, 0.6277, 0.4026, 1.03, 0.5663, -0.0526, 0.7858, -0.3533, -0.0985, 0.9309, 0.0741, -0.2277, 0.685, 0.2433, 0.1442, 0.2823, 0.1612]}, "token.table": {"Topic": [1, 4, 1, 2, 3, 4, 5, 5, 3, 3, 2, 5, 4, 2, 2, 2, 5, 1, 5, 2, 3, 4, 4, 1, 2, 5, 1, 1, 2, 3, 4, 5, 4, 4, 1, 5, 4, 1, 2, 4, 2, 2, 4, 2, 3, 1, 2, 4, 2, 4, 5, 4, 2, 3, 4, 4, 5, 4, 5, 3, 3, 2, 3, 2, 5, 2, 5, 5, 4, 3, 3, 5, 4, 2, 4, 2, 3, 1, 5, 2, 3, 3, 1, 2, 3, 5, 5, 1, 3, 5, 3, 3, 3, 1, 2, 5, 1, 2, 3, 4, 5, 3, 1, 2, 3, 4, 5, 3, 4, 1, 2, 3, 5, 1, 2, 2, 1, 3, 5, 1, 5, 2, 1, 4, 4, 3, 5, 1, 1, 2, 3, 4, 4, 5, 1, 2, 3, 2, 3, 4, 5, 1, 2, 3, 4, 5, 1, 5, 1, 2, 4, 5, 3, 1, 2, 3, 1, 1, 5, 1, 1, 2, 3, 4, 5, 2, 4, 5, 1, 3, 5, 5, 1, 2, 3, 5, 1, 1, 3, 5, 1, 3, 4, 5, 1, 2, 3, 4, 5, 2, 3, 5, 5, 1, 2, 3, 4, 5, 1, 1, 2, 3, 4, 5, 5, 2, 1, 2, 3, 4, 5, 1, 2, 3, 4, 5, 2, 3, 1, 3, 5, 1, 2, 3, 4, 5, 2, 4, 5, 4, 1, 3, 3, 4, 5, 1, 4, 5, 1, 2, 3, 4, 5, 2, 5, 5, 1, 2, 3, 4, 2, 5, 2, 3, 2, 1, 2, 3, 5, 5, 4, 1, 2, 3, 5, 3, 5, 2, 1, 3, 4, 5, 2, 2, 1, 2, 3, 4, 5, 2, 2, 4, 4, 2, 5, 1, 4, 5, 1, 2, 4, 2, 3, 4, 5, 2, 3, 4, 5, 1, 2, 1, 2, 3, 4, 5, 4, 5, 1, 2, 3, 4, 5, 1, 1, 2, 4, 5, 1, 1, 2, 3, 5, 5, 1, 3, 4, 1, 2, 3, 1, 3, 4, 5, 5, 1, 2, 3, 5, 1, 2, 5, 2, 1, 5, 1, 1, 2, 3, 4, 1, 3, 5, 3, 1, 2, 3, 4, 5, 4, 1, 3, 4, 5, 5, 1, 2, 4, 2, 3, 1, 2, 3, 4, 5, 3, 4, 3, 1, 2, 3, 4, 5, 1, 3, 5, 1, 1, 3, 4, 5, 3, 5, 2, 2, 3, 4, 5, 1, 4, 1, 2, 3, 5, 4, 5, 5, 2, 4, 4, 2, 2, 3, 1, 3, 3, 4, 1, 2, 3, 4, 5, 1, 2, 5, 1, 4, 1, 2, 3, 4, 5, 5, 1, 2, 3, 4, 5, 5, 2, 4, 2, 2, 3, 4, 1, 2, 3, 4, 5, 1, 3, 5, 3, 3, 5, 2, 3, 4, 1, 2, 3, 4, 5, 1, 2, 3, 4, 5, 2, 4, 4, 1, 4, 3, 2, 1, 2, 3, 4, 5, 1, 3, 4, 3, 4, 5, 1, 2, 3, 4, 4, 1, 3, 2, 1, 3, 1, 1, 2, 3, 4, 5, 1, 2, 3, 4, 5, 3, 4, 5, 2, 1, 3, 5, 4, 2, 3, 4, 1, 4, 5, 1, 2, 3, 4, 5, 2, 3, 4, 1, 2, 3, 4, 5, 1, 2, 3, 4, 5, 1, 2, 3, 4, 5, 1], "Freq": [0.8640450098171444, 0.4671073996020494, 0.1439086658663772, 0.2014721322129281, 0.31659906490602985, 0.08634519951982632, 0.23025386538620352, 0.8868681396566506, 0.8884756786914647, 0.8192150370695345, 0.7476900077384503, 0.8282287659332445, 0.8589826437089936, 0.7477189346165909, 0.7477370194495345, 0.9500338229382698, 0.9833392624105765, 0.7024548820931802, 0.23415162736439338, 0.09617321526679755, 0.865558937401178, 0.048086607633398774, 0.46710137094294457, 0.05407408260266257, 0.7029630738346134, 0.21629633041065027, 0.7759277303676839, 0.06434340635399352, 0.22520192223897734, 0.3860604381239611, 0.09651510953099028, 0.2573736254159741, 0.4671786332878215, 0.9681303291572746, 0.8640720840733768, 0.8869040568496345, 0.9754721206951448, 0.3234843143049331, 0.5391405238415551, 0.16174215715246654, 0.7477106524895789, 0.34826253270020063, 0.6965250654004013, 0.9674035219038509, 0.8192556233599737, 0.07019997115981953, 0.21059991347945858, 0.7019997115981953, 0.28951902444256233, 0.4825317074042706, 0.28951902444256233, 0.9398240856128294, 0.7476967359634047, 0.8188531540149073, 0.4671562215885668, 0.6192484341669064, 0.3096242170834532, 0.6983817935488926, 0.2618931725808348, 0.9818362953649598, 0.9562860114944475, 0.16680967413754783, 0.8155139624502339, 0.8302187426756253, 0.7460336716357785, 0.9764938603493276, 0.9308382059542556, 0.9298832380071806, 0.467142517877966, 0.976792640420915, 0.9862024336422558, 0.9291606593253342, 0.4671178440779488, 0.37793475326723297, 0.6298912554453883, 0.08177509184240943, 0.8995260102665037, 0.8628664160912481, 0.7460166738967122, 0.7477080613923642, 0.858339480174906, 0.8582899588125333, 0.04063591064668016, 0.6095386597002024, 0.20317955323340078, 0.12190773194004047, 0.8868314369994301, 0.6599624173662739, 0.2639849669465096, 0.0659962417366274, 0.8887366279377641, 0.9798187006631194, 0.8187792365190257, 0.9250194354141109, 0.7304513099823546, 0.21913539299470638, 0.0977882947404965, 0.16501774737458783, 0.4950532421237635, 0.055005915791529275, 0.18946482105971196, 0.9234531694048919, 0.07009747993520488, 0.24033421692070245, 0.5040342604864732, 0.04339367805512683, 0.14019495987040975, 0.9235627478040265, 0.4671126885998348, 0.37318415022774276, 0.12439471674258093, 0.4664801877846785, 0.031098679185645232, 0.07794043645942299, 0.8963150192833644, 0.88905423850082, 0.8158860435996383, 0.11655514908566263, 0.9649714210823297, 0.13879951112956013, 0.7633973112125807, 0.8301458926647705, 0.7758919841157914, 0.4671818383147537, 0.4671164815344839, 0.8584067523192499, 0.8868819791797854, 0.8641521267192512, 0.574804550340857, 0.14370113758521424, 0.14370113758521424, 0.14370113758521424, 0.046131098589510186, 0.9226219717902038, 0.6809610963242467, 0.09728015661774954, 0.19456031323549908, 0.7477636259007661, 0.7408157060257843, 0.18520392650644607, 0.04630098162661152, 0.20861002977773221, 0.44702149238085476, 0.17880859695234189, 0.08940429847617094, 0.08940429847617094, 0.7756624529821065, 0.9308256280388425, 0.15642658188793804, 0.7821329094396902, 0.858860577141131, 0.7460091788354872, 0.9231233264228063, 0.1655996416919116, 0.7451983876136022, 0.0827998208459558, 0.8980564313210945, 0.7727981677822036, 0.17173292617382302, 0.7758124005618259, 0.1801257698011447, 0.060041923267048235, 0.060041923267048235, 0.060041923267048235, 0.6004192326704824, 0.10625831602984594, 0.10625831602984594, 0.7438082122089216, 0.866916088669114, 0.049538062209663655, 0.07430709331449548, 0.7460105969435232, 0.24114280378809652, 0.3726752422179674, 0.043844146143290276, 0.3507531691463222, 0.9596062247301141, 0.6965466684018, 0.11609111140030001, 0.11609111140030001, 0.5432878355084831, 0.24146126022599249, 0.06036531505649812, 0.12073063011299624, 0.12962872125064656, 0.08641914750043105, 0.47530531125237074, 0.2592574425012931, 0.08641914750043105, 0.8890353899164257, 0.9367962907160793, 0.10408847674623103, 0.7459821869598485, 0.2646350871323442, 0.14624570604682177, 0.38302446821786656, 0.020892243720974542, 0.18106611224844602, 0.9431046150770541, 0.5240835591330429, 0.058231506570338105, 0.1746945197110143, 0.11646301314067621, 0.1746945197110143, 0.7460176595344917, 0.7476801889722526, 0.1061737965782369, 0.05308689828911845, 0.2654344914455922, 0.2654344914455922, 0.31852138973471067, 0.06544030741162615, 0.032720153705813076, 0.6544030741162614, 0.032720153705813076, 0.2290410759406915, 0.08817177388888534, 0.8817177388888533, 0.022229511301083412, 0.5557377825270854, 0.4001312034195014, 0.1606730911921663, 0.10711539412811087, 0.19637822256820325, 0.1785256568801848, 0.37490387944838804, 0.10624749055706369, 0.10624749055706369, 0.7437324338994458, 0.46713480222562986, 0.7799202768937497, 0.1949800692234374, 0.8190442230472239, 0.8370290448270504, 0.11957557783243578, 0.8317925982597018, 0.03080713326887784, 0.12322853307551136, 0.4207448713436296, 0.04207448713436296, 0.08414897426872592, 0.2103724356718148, 0.25244692280617775, 0.15497101434064645, 0.8523405788735554, 0.8869089555327008, 0.05022172763374982, 0.8035476421399971, 0.05022172763374982, 0.05022172763374982, 0.745738255319289, 0.24857941843976297, 0.9105948814279609, 0.06504249153056862, 0.7476880439386745, 0.15533566678961014, 0.07766783339480507, 0.07766783339480507, 0.6213426671584406, 0.7460244470275872, 0.4671183199129401, 0.1686534722632476, 0.1686534722632476, 0.11243564817549839, 0.5059604167897428, 0.7884866006445419, 0.21026309350521116, 0.8704313043376758, 0.3060540302315728, 0.0382567537789466, 0.191283768894733, 0.4208242915684126, 0.7476729476067281, 0.9674125476784445, 0.11893917175575099, 0.019823195292625165, 0.7532814211197563, 0.019823195292625165, 0.05946958587787549, 0.7476633811042359, 0.45074608912682096, 0.45074608912682096, 0.9535863121119973, 0.15520907315983026, 0.7760453657991513, 0.017537408351612382, 0.3156733503290229, 0.6488841090096581, 0.1286863771152849, 0.1286863771152849, 0.7721182626917095, 0.7680969137134349, 0.15361938274268697, 0.85888538185104, 0.7460059476733386, 0.5781109064129023, 0.3211727257849457, 0.06423454515698915, 0.06423454515698915, 0.7757760546312175, 0.966206803365562, 0.15173182860165604, 0.09103909716099362, 0.6676200458472866, 0.060692731440662416, 0.030346365720331208, 0.5186165553207908, 0.34574437021386056, 0.06204765263459188, 0.18614295790377564, 0.12409530526918376, 0.06204765263459188, 0.5584288737113269, 0.9080188264161034, 0.32069569056054775, 0.5344928176009129, 0.10689856352018258, 0.05344928176009129, 0.9250507143102669, 0.2769232623119812, 0.18461550820798747, 0.5230772732559645, 0.030769251367997914, 0.7460280944679145, 0.8625725730240039, 0.3023259331556374, 0.6046518663112748, 0.08244349058188045, 0.08244349058188045, 0.8244349058188046, 0.017370336349900612, 0.9032574901948319, 0.017370336349900612, 0.05211100904970184, 0.7459904495103451, 0.02653992498392116, 0.02653992498392116, 0.9023574494533194, 0.02653992498392116, 0.6977064727847452, 0.11628441213079087, 0.11628441213079087, 0.7476895621410283, 0.5896060708375525, 0.2948030354187762, 0.9717523930031143, 0.30683946036046145, 0.07670986509011536, 0.30683946036046145, 0.30683946036046145, 0.08694900426183141, 0.21737251065457852, 0.6521175319637356, 0.9557083067946295, 0.12313009977013736, 0.18469514965520603, 0.36939029931041206, 0.24626019954027473, 0.09234757482760302, 0.4671325331839061, 0.08272934409867881, 0.70319942483877, 0.14477635217268792, 0.06204700807400911, 0.9649878337447629, 0.1051159779573643, 0.3153479338720929, 0.5255798897868215, 0.03787766660588034, 0.9469416651470086, 0.04094131707226731, 0.21835369105209232, 0.30023632519662696, 0.1364710569075577, 0.30023632519662696, 0.33674717200733456, 0.6734943440146691, 0.8190193652948018, 0.2500138361662549, 0.16667589077750325, 0.16667589077750325, 0.2500138361662549, 0.16667589077750325, 0.10260033688545196, 0.10260033688545196, 0.7182023581981637, 0.7756705770578814, 0.1543870505128678, 0.6561449646796881, 0.0771935252564339, 0.11579028788465084, 0.30254667239543703, 0.6807300128897333, 0.9674364394125105, 0.13336872827826424, 0.4445624275942141, 0.04445624275942141, 0.40010618483479266, 0.2029256170178932, 0.7102396595626261, 0.38707951805529833, 0.17203534135791035, 0.17203534135791035, 0.25805301203686554, 0.4671243944664717, 0.7460268967459489, 0.7460283313129705, 0.6514274604276072, 0.2791831973261174, 0.4671812241482198, 0.7476810964356078, 0.683491425396576, 0.1366982850793152, 0.8140885409478, 0.11629836299254287, 0.888535224078785, 0.7196304868044219, 0.4355111486138761, 0.14517038287129203, 0.24195063811882003, 0.04839012762376401, 0.09678025524752802, 0.7731281106805309, 0.12407373981502504, 0.8685161787051753, 0.8632222764522789, 0.46713655628030065, 0.14187397304000718, 0.14187397304000718, 0.4823715083360244, 0.11349917843200574, 0.14187397304000718, 0.901853288585017, 0.07439996911470084, 0.07439996911470084, 0.706799706589658, 0.11159995367205126, 0.07439996911470084, 0.7459585961255963, 0.8442040447150541, 0.1407006741191757, 0.9323003035955106, 0.7161824483115266, 0.07957582759016961, 0.15915165518033922, 0.07639941676185627, 0.3055976670474251, 0.3819970838092813, 0.07639941676185627, 0.1145991251427844, 0.8645829591908736, 0.8886447405714333, 0.746031078225386, 0.8602784266762036, 0.05872467952248585, 0.8808701928372877, 0.668211218503777, 0.16705280462594424, 0.08352640231297212, 0.1805394577481321, 0.2063308088550081, 0.30949621328251214, 0.07737405332062804, 0.23212215996188412, 0.20774406459657282, 0.029677723513796116, 0.6825876408173107, 0.029677723513796116, 0.05935544702759223, 0.2326817523115443, 0.6980452569346329, 0.8589691826312279, 0.8223264131143901, 0.16446528262287805, 0.957911028409963, 0.7476820628602079, 0.25123672399788516, 0.03589096057112645, 0.1435638422845058, 0.0717819211422529, 0.5024734479957703, 0.7949588371703323, 0.15899176743406646, 0.9596677586457044, 0.10386724472383141, 0.10386724472383141, 0.7270707130668198, 0.05535520613935592, 0.05535520613935592, 0.8303280920903388, 0.05535520613935592, 0.8256795792425449, 0.775987760251429, 0.8192475502992072, 0.7476952803018264, 0.8141877250469289, 0.11631253214956128, 0.7759403226995054, 0.06327105501314156, 0.12654211002628313, 0.3796263300788494, 0.20563092879271008, 0.22144869254599547, 0.11431901263200102, 0.22863802526400204, 0.34295703789600307, 0.08573925947400077, 0.2572177784220023, 0.1498067558998261, 0.44942026769947824, 0.2996135117996522, 0.8301743615850403, 0.7756406637581996, 0.7982340627664558, 0.17738534728143462, 0.8589765617297854, 0.704386017066954, 0.15653022601487868, 0.07826511300743934, 0.1972567481169136, 0.5917702443507409, 0.1972567481169136, 0.2029218814820842, 0.18601172469191052, 0.45657423333468944, 0.06764062716069473, 0.06764062716069473, 0.700797914670175, 0.2156301275908231, 0.05390753189770577, 0.07112822236701372, 0.33193170437939734, 0.3082222969237261, 0.09483762982268495, 0.16596585218969867, 0.25115461689688395, 0.2930137197130313, 0.313943271121105, 0.06278865422422099, 0.10464775704036831, 0.1813840459269269, 0.3224605260923145, 0.29222985177116, 0.05038445720192414, 0.16123026304615726, 0.7759170862407717], "Term": ["2030", "Al-Shifa Hospital", "Articles", "Articles", "Articles", "Articles", "Articles", "Auschwitz", "Baer", "Belgrade", "Berisha", "Bieri", "Carboni", "Charkiv", "Darya Kaysina", "Dea Gjinovci", "Destinus", "Dubai", "Dubai", "EU", "EU", "EU", "Eli Cohen", "English", "English", "English", "Erika Lennon", "Europe", "Europe", "Europe", "Europe", "Europe", "FSCI", "Fabrizio Carboni", "Felix Wertli", "Gaspard Stockalper", "Gaza", "Geneva", "Geneva", "Geneva", "HHLA", "Hamas", "Hamas", "Hamburg", "Hashim Thaci", "ICRC", "ICRC", "ICRC", "Israel", "Israel", "Israel", "Israeli", "Jan Tiedemann", "Jensen", "Jew", "Jewish", "Jewish", "Jews", "Jews", "KFOR", "KLA", "Kosovo", "Kosovo", "Larisa Verbitskaya", "London", "MSC", "Martina L\u00f6fqvist", "Mikhail Kokorich", "Monika B\u00fctler", "NATO", "Nato", "Nina Weil", "October 7", "Palestinian", "Palestinian", "Parliament", "Parliament", "Patrick Hofstetter", "Payerne", "Polish", "Pro Switzerland", "Rietiker", "Russian", "Russian", "Russian", "Russian", "SSR", "SWI", "SWI", "SWI", "SWISSCOY", "Serbia", "Silja H\u00e4usermann", "South Pole", "Spanish", "Spanish", "Swiss", "Swiss", "Swiss", "Swiss", "Swiss", "Swisscoy", "Switzerland", "Switzerland", "Switzerland", "Switzerland", "Switzerland", "Thaci", "The Geneva Conventions", "Ukraine", "Ukraine", "Ukraine", "Ukraine", "Ukrainian", "Ukrainian", "Ukrainians", "United Nations", "United Nations", "Urs Bieri", "Valais", "Valais", "Vietnamese", "Wertli", "World War II", "ability", "accession", "aerospace", "agency", "agreement", "agreement", "agreement", "agreement", "aircraft", "aircraft", "analysis", "analysis", "analysis", "apartment", "army", "army", "army", "article", "article", "article", "article", "article", "atmosphere", "aviation", "bar", "bar", "battlefield", "bracelet", "burn", "business", "business", "business", "c", "carbon", "carbon", "certification", "challenge", "challenge", "challenge", "challenge", "challenge", "class", "class", "class", "climate", "climate", "climate", "combustion", "company", "company", "company", "company", "compensation", "conference", "conference", "conference", "confidence", "confidence", "confidence", "confidence", "conflict", "conflict", "conflict", "conflict", "conflict", "container", "cooperation", "cooperation", "corruption", "country", "country", "country", "country", "country", "credit", "crisis", "crisis", "crisis", "crisis", "crisis", "dance", "datum", "day", "day", "day", "day", "day", "debate", "debate", "debate", "debate", "debate", "decision", "decision", "democracy", "democracy", "democracy", "development", "development", "development", "development", "development", "dialogue", "dialogue", "dialogue", "economist", "effort", "effort", "electorate", "electricity", "electricity", "emission", "emission", "emission", "energy", "energy", "energy", "energy", "energy", "engine", "engine", "entrepreneur", "family", "family", "family", "family", "figure", "figure", "film", "film", "filmmaker", "flight", "flight", "flight", "flight", "footprint", "four-day", "franc", "franc", "franc", "franc", "freedom", "freedom", "freight", "fuel", "fuel", "fuel", "fuel", "gender", "gold", "government", "government", "government", "government", "government", "help", "hospital", "hospital", "hostage", "husband", "husband", "hydrogen", "hydrogen", "hydrogen", "icrc", "icrc", "icrc", "immigration", "immigration", "intermediary", "investor", "job", "job", "job", "job", "justice", "labour", "law", "law", "law", "law", "law", "liberation", "liberation", "life", "life", "life", "life", "life", "lift", "market", "market", "market", "market", "mechanism", "member", "member", "member", "member", "meter", "method", "middle", "middle", "minister", "minister", "minister", "mission", "mission", "mission", "mission", "mistake", "neutrality", "neutrality", "neutrality", "neutrality", "newsletter", "newsletter", "newsletter", "north", "objective", "objective", "oil", "operation", "operation", "operation", "operation", "opinion", "opinion", "opinion", "out", "part", "part", "part", "part", "part", "parttime", "party", "party", "party", "party", "passenger", "past", "past", "past", "peace", "peace", "people", "people", "people", "people", "people", "percent", "percent", "pillar", "place", "place", "place", "place", "place", "plane", "plane", "plane", "planting", "policy", "policy", "policy", "policy", "politician", "politician", "port", "power", "power", "power", "power", "prisoner", "prisoner", "project", "project", "project", "project", "promise", "propulsion", "prototype", "rate", "rate", "reader", "record", "recruitment", "recruitment", "reduction", "reduction", "referendum", "release", "report", "report", "report", "report", "report", "reporter", "residence", "residence", "resort", "rest", "right", "right", "right", "right", "right", "salt", "security", "security", "security", "security", "security", "selection", "ship", "ship", "shipping", "shortage", "shortage", "shortage", "situation", "situation", "situation", "situation", "situation", "ski", "solidarity", "sound", "speech", "speed", "speed", "staff", "staff", "staff", "standard", "standard", "standard", "standard", "standard", "state", "state", "state", "state", "state", "stereotype", "stereotype", "store", "strategy", "strategy", "stress", "subject", "system", "system", "system", "system", "system", "target", "target", "tax", "technology", "technology", "technology", "the Federal Council", "the Federal Council", "the Federal Council", "the Federal Council", "the Gaza Strip", "the Human Rights Council", "the Ukraine war", "the United Kingdom", "the United Nations", "the United Nations", "the United Nations Environment Programme", "time", "time", "time", "time", "time", "today", "today", "today", "today", "today", "transition", "transition", "transition", "trauma", "tree", "troop", "troop", "truce", "violence", "violence", "violence", "visit", "visit", "visit", "war", "war", "war", "war", "war", "woman", "woman", "woman", "work", "work", "work", "work", "work", "world", "world", "world", "world", "world", "year", "year", "year", "year", "year", "\u00b0"]}, "R": 30, "lambda.step": 0.01, "plot.opts": {"xlab": "PC1", "ylab": "PC2"}, "topic.order": [1, 2, 3, 4, 5]}