{"mdsDat": {"x": [0.0045411549817617825, 0.004777958308634084, 0.03223057524316395, -0.1481887581064623, 0.10663906957290245], "y": [-0.007949406073276098, -0.008100200564598207, 0.14120972498067233, -0.034809737570719576, -0.09035038077207853], "topics": [1, 2, 3, 4, 5], "cluster": [1, 1, 1, 1, 1], "Freq": [0.07161476566064964, 0.07161531481498809, 21.279846357908728, 16.966445895194347, 61.61047766642129]}, "tinfo": {"Term": ["Swiss", "election", "emission", "company", "party", "watch", "compensation", "climate", "carbon", "industry", "agreement", "state", "Abdeslam Bouchouareb", "country", "c", "request", "conference", "Chakib Khelil", "credit", "oil", "corruption", "Switzerland", "reduction", "solution", "-", "term", "UDC", "right", "component", "market", "polarization", "Lisa Mazzone", "moderator", "personality", "mark", "brake", "wave", "introduction", "rotation", "ecologist", "weakness", "house", "Zurich", "Chambers", "hope", "recent years", "blockage", "liberal", "style", "Houses of Parliament", "minority", "elective", "this election Sunday", "lifestyle", "bourgeois", "lesson", "Lukas Golder", "the Greens\u2019 Liberals", "the next 20 years", "Vert-e-s", "s", "supply", "how", "brand", "scourge", "destruction", "interest", "precision", "know", "debate", "competition", "pride", "the Federal Office of Intellectual Property", "More\n\nImmigration", "dialogue", "Hong Kong", "retortion", "1956", "shortage", "fh", "reverence", "the University of Neuch\u00e2tel", "suppression", "taxis", "luxury", "Vaud", "director", "framework", "discrimination", "ad", "the Federation of Swiss watch industry", "Swiss", "company", "climate", "watch", "country", "Switzerland", "term", "year", "emission", "industry", "solution", "component", "market", "transfer", "process", "technology", "law", "fabric", "capital", "volume", "watchmaking", "compensation", "election", "carbon", "policy", "authority", "reduction", "-", "president", "agreement", "risk", "energy", "project", "moderator", "handicap", "recipe", "mark", "blockage", "backguard", "minority", "house", "Zurich", "Marianne Binder-Keller", "symbol", "Le Centre", "liberal", "hope", "rotation", "wave", "polarization", "personality", "non", "Lukas Golder", "recent years", "2019", "Houses of Parliament", "the next 20 years", "trend", "Vert\u2019lib\u00e9raux", "factor", "cost", "brake", "elective", "positioning", "detection", "manoeuvre", "text", "frustration", "growth", "implementation", "mandate", "movement", "the end of December 2023", "discrimination", "economy", "challenge", "input", "the Brand Division", "margin", "tension", "Counterfeiting", "announcement", "material", "EU", "1956", "Hong Kong", "know", "statistic", "2000", "ability", "pride", "fight", "director", "dialogue", "Swiss", "company", "climate", "country", "Switzerland", "emission", "year", "watch", "compensation", "reduction", "project", "market", "term", "industry", "component", "state", "%", "agreement", "sector", "commitment", "Jean-Daniel Pasche", "request", "authority", "law", "limit", "standard", "franc", "carbon", "actor", "case", "election", "policy", "president", "c", "industry", "component", "transfer", "process", "actor", "Jean-Daniel Pasche", "technology", "capital", "volume", "Swissness", "watchmaking", "watch", "counterfeiting", "fabric", "Brazil", "product", "segment", "export", "subcontractor", "label", "India", "doctor", "supply", "scourge", "announcement", "the last two years", "issue", "luxury", "object", "condition", "Swiss", "term", "analysis", "legislation", "company", "market", "law", "property", "Switzerland", "year", "solution", "risk", "president", "authority", "example", "consumer", "production", "party", "UDC", "right", "alliance", "PLR", "area", "e", "majority", "seat", "idea", "training", "the Council of States", "electorate", "the National Council", "share", "compromise", "defeat", "force", "role", "Parliament", "health", "left", "city", "Centre", "election", "element", "hope", "minority", "thing", "Genevan", "theme", "-", "centre", "solution", "risk", "policy", "Switzerland", "term", "climate", "year", "loss", "level", "campaign", "citizen", "possibility", "emission", "compensation", "carbon", "agreement", "Abdeslam Bouchouareb", "state", "credit", "oil", "request", "corruption", "c", "Chakib Khelil", "conference", "limit", "Geneva", "today", "article", "fund", "report", "2030", "Algeria", "objective", "fuel", "Wertli", "Dubai", "the Federal Office of Justice", "climate", "country", "amount", "official", "reduction", "project", "year", "company", "Swiss", "franc", "case", "Switzerland", "%", "authority"], "Freq": [22.0, 7.0, 14.0, 15.0, 6.0, 7.0, 10.0, 17.0, 8.0, 5.0, 5.0, 5.0, 5.0, 18.0, 4.0, 4.0, 4.0, 4.0, 4.0, 4.0, 4.0, 14.0, 7.0, 5.0, 5.0, 6.0, 3.0, 3.0, 3.0, 5.0, 0.0014020955428675735, 0.0014016140418671463, 0.0014015314723314274, 0.0014014755755389885, 0.001401436494171661, 0.0014014719805170682, 0.0014014341748026802, 0.00140142327376847, 0.0014014237376422662, 0.0014014078499647474, 0.0014013496338033276, 0.0014012655566777714, 0.001401227055152689, 0.0014012205609195427, 0.0014011260466335724, 0.001401170810454903, 0.0014011555026196294, 0.0014011365997624353, 0.0014012069926110046, 0.0014011426301217857, 0.0014010478838989173, 0.0014011049403758467, 0.001401124886949082, 0.0014011110867036458, 0.0014010798911908533, 0.001401063075765742, 0.0014009792305770838, 0.0014010505511732453, 0.001400907794012473, 0.0014009242615322373, 0.0014009283204279538, 0.001406713290540025, 0.0014057059885916356, 0.0014056329284687385, 0.001405535283034644, 0.0014055286728330487, 0.0014055124372501825, 0.001405457584173785, 0.001405376290291006, 0.0014053732751113308, 0.001405360982455732, 0.001405317726224239, 0.0014052648446114752, 0.0014052117310618135, 0.0014051235950405406, 0.0014050702495539808, 0.001405075932007984, 0.0014049920868193257, 0.0014049829253118514, 0.001404963906486208, 0.0014049344505001511, 0.0014049249410873297, 0.0014049165913589986, 0.0014049169392643457, 0.001404855939860149, 0.0014048510691852892, 0.0014048380807189964, 0.0014047954043297484, 0.0014047879823490097, 0.0014047776611570448, 0.001404775573724962, 0.001512013570018846, 0.0014817070713565893, 0.0014754081290783588, 0.0014500359719544415, 0.0014608043382587973, 0.0014572800570923743, 0.0014444257662950784, 0.0014535953915609245, 0.0014532111880892445, 0.0014347813661988494, 0.0014336047503148571, 0.0014275066653903694, 0.001432608465369127, 0.0014202694223909302, 0.0014199024982181575, 0.0014181415173194364, 0.0014251012478203153, 0.0014124901428606632, 0.0014168002262378028, 0.0014166608321620527, 0.001416599716789407, 0.0014335460702796412, 0.001428844825323879, 0.0014243167212625379, 0.0014234615699192934, 0.0014213946642519964, 0.0014202338200770739, 0.0014199614101902715, 0.0014193181332034287, 0.0014189436710814684, 0.0014188955441751154, 0.001418661403876497, 0.0014176140928131879, 0.0013985707371602775, 0.001398632084940243, 0.0013986361438670838, 0.001398433313494381, 0.001398480976892426, 0.0013984758742415404, 0.0013983367110355694, 0.0013982599393336087, 0.001398231874753738, 0.0013983219829296041, 0.00139830992211842, 0.0013982688689726586, 0.0013981997512470263, 0.0013981600897333246, 0.0013981907056386381, 0.0013981215879130058, 0.0013980419169775874, 0.0013980568770222293, 0.001398137011835001, 0.0013981261107172, 0.0013980934073637968, 0.0013981687874336977, 0.001398051078555314, 0.0013980399454988361, 0.0013981466372900806, 0.0013981244871464635, 0.0013980951469038713, 0.0013980152440297763, 0.001397912031318681, 0.0013979230484058205, 0.0013979715235892336, 0.0014033988886221049, 0.0014032465049115667, 0.0014030659406518192, 0.0014027528234383843, 0.0014027357759456528, 0.0014027066676417371, 0.0014026449719537566, 0.0014026174872205774, 0.0014025596185207611, 0.0014025451223534725, 0.0014025460501081788, 0.0014025389759785422, 0.0014024954874766761, 0.0014024497955573824, 0.0014024439970904668, 0.001402443301274437, 0.001402366413603138, 0.0014023337102497349, 0.0014023246646413467, 0.001402295904245446, 0.0014022658681868238, 0.001402256590639759, 0.0014022500963568139, 0.0014022563587010825, 0.0014022432541658536, 0.001402245689521958, 0.0014022291059065798, 0.0014022335127414356, 0.0014022104348431121, 0.00140218039878449, 0.0015482563050734817, 0.0015016804674830588, 0.0015035941935038373, 0.0014989782659311159, 0.001480587152446011, 0.0014730264154656034, 0.0014685596244619474, 0.0014525751066854352, 0.001456990407302882, 0.0014502667370063903, 0.001442852353330929, 0.0014373187603841668, 0.0014389366486229186, 0.0014314188202976855, 0.0014256108438964834, 0.0014295737481251859, 0.0014280550136706884, 0.001429039361414257, 0.0014252766202634763, 0.0014220326099629527, 0.0014158853072778579, 0.0014250834153458531, 0.0014265034598934495, 0.0014230355128006507, 0.0014218060058758964, 0.0014233397003750358, 0.001426415903043026, 0.0014319131975868977, 0.0014145774050804067, 0.0014255545987674036, 0.001424739798196443, 0.0014236262606099979, 0.0014235099433636737, 0.0014234436089021608, 4.861299713990552, 3.5104063252744586, 2.160638513347302, 2.1604498145199624, 2.1606652537216657, 2.160362701547809, 2.160515700597003, 2.1604715927630007, 2.1604168714814422, 2.1607497477911757, 2.1605578787132673, 6.211643960173321, 1.485656329616088, 1.485386996154714, 1.4854594984068545, 1.485515735895207, 1.4853788637728198, 1.485430139129847, 1.485570043665822, 1.4852727292972527, 1.485423109443803, 1.4854825171827242, 0.8103418898415568, 0.8104734552401656, 0.8104762808982813, 0.8104864119164036, 0.8104634620590244, 0.8104735241586561, 0.8104926145805601, 0.8105179765851112, 10.263044999135543, 3.511411432541777, 1.4857427534033356, 1.4854250391615405, 6.212190897314945, 2.8355661136339383, 2.160401571576523, 1.4856666673896823, 3.513938535756124, 2.1623833916930213, 1.4874502779271344, 1.4870231211222222, 1.4868247737061948, 1.486158194064841, 1.4860787999636376, 1.4857561235905175, 1.4855989894318855, 5.7318372498879535, 3.239833942106139, 3.238963992837812, 2.617274683649838, 2.6166111220426935, 1.9938619605626857, 1.9937485462568603, 1.9935208384645444, 1.9935094091158954, 1.9933942364487394, 1.9934907265267574, 1.993399291737565, 1.9929260727444607, 1.371000483752684, 1.3706605705279575, 1.3707862933630972, 1.370486602653809, 1.3706429869146513, 1.3706002367548005, 1.3704766019737409, 1.3704764920761578, 1.3705605637272782, 1.3705807848825804, 1.3704128613755058, 5.732308490724561, 0.7479380042630752, 0.7478430527512215, 0.7478248097524163, 0.7479236626284723, 0.7478603066717783, 1.9941613215792244, 3.2406168524885994, 1.9941547277242346, 3.2407863145618383, 1.9937590964248442, 2.618211450648728, 3.2454264103181902, 1.995427781327607, 1.3788535452504198, 1.3778371025037357, 1.3720036288918054, 1.371769656937249, 1.371322703466521, 1.3712280816474167, 1.3711697260307565, 14.720173606124826, 10.438616950426109, 7.873439346975304, 5.305603521361096, 5.306687402369324, 5.305350110300631, 4.450278138829205, 4.450243818591095, 4.449503539036507, 4.450460115905697, 4.448891760838563, 4.449241747452781, 4.44885265173002, 3.595684256256107, 3.596611700830157, 3.596092906533141, 3.594868551992183, 3.5948050994589327, 3.5942567737942404, 3.5944535165545703, 3.5946255168176577, 3.5942196600483767, 3.5936134688659402, 3.594207687872292, 3.594131465017884, 3.5938090144086616, 16.430898598680333, 16.430422904217224, 2.7416985602281256, 2.7397610630650386, 7.020353160443841, 6.1628923407709255, 11.302289733196988, 9.58779749590007, 12.161893572389117, 4.455929005941319, 4.4510383720106015, 7.880239542991576, 3.596882272009678, 3.5950876428145384], "Total": [22.0, 7.0, 14.0, 15.0, 6.0, 7.0, 10.0, 17.0, 8.0, 5.0, 5.0, 5.0, 5.0, 18.0, 4.0, 4.0, 4.0, 4.0, 4.0, 4.0, 4.0, 14.0, 7.0, 5.0, 5.0, 6.0, 3.0, 3.0, 3.0, 5.0, 1.0584589173853713, 1.0585223083579913, 1.058482957339958, 1.0585109703694904, 1.0584828909944106, 1.0585349008001894, 1.0585171234783444, 1.058564439560573, 1.058568558792834, 1.0585687713602536, 1.0585907915203003, 1.05853182764261, 1.058530855204039, 1.0585786663740533, 1.0585199450308538, 1.0585613918282533, 1.0585515317907725, 1.05854327561129, 1.0586017336553697, 1.0585711705244334, 1.0585019158130065, 1.058547711041132, 1.0586331622557423, 1.0586294256361695, 1.0586225133529015, 1.0586230473274196, 1.0585694975442774, 1.0586538775336216, 1.0585636075697284, 1.0586233294571372, 1.0586297328841396, 1.1101147089174472, 1.110312344141467, 1.1102864924861584, 1.1103159261709645, 1.1103440776521054, 1.1102450219657962, 1.1102187009869837, 1.1101851766609223, 1.1102545540487, 1.1103582202336777, 1.1102203938557804, 1.1103686946468303, 1.1103296367263056, 1.1102306546522678, 1.1102255936381615, 1.1103307849832458, 1.1102402923153172, 1.1104062073076024, 1.1104083684322255, 1.110271568064093, 1.1103096533110057, 1.1102938517949492, 1.1103494696041225, 1.1103601241253387, 1.1103306377072104, 1.1102705261685595, 1.1102976724729403, 1.1102263416849762, 1.1103904562210651, 1.1104139427582675, 22.56414665743874, 15.937220813825329, 17.950912831954987, 7.374110082952241, 18.004977815008107, 14.642542356275428, 6.541522822715587, 14.845432382409768, 14.993107994245927, 5.166564550004806, 5.762697722546733, 3.813901994378811, 5.706528833173205, 2.461942803359017, 2.4617675381562543, 2.462045235451206, 4.17442678062026, 1.7860862450998418, 2.4620300357681515, 2.4620575081427094, 2.4625301791748804, 10.710215086403823, 7.763827722569217, 8.14259789571922, 5.3185334365112515, 5.211657890411901, 7.961687610817176, 5.0864601466547334, 4.979606306369538, 5.571983602757711, 3.6581196803351217, 4.5350896317776375, 7.105071679808904, 1.058482957339958, 1.058546474978908, 1.058592699782166, 1.0584828909944106, 1.0585515317907725, 1.0585800396117206, 1.0585019158130065, 1.05853182764261, 1.058530855204039, 1.0586022981564982, 1.0586120731130733, 1.0585850790393356, 1.05854327561129, 1.0585199450308538, 1.058568558792834, 1.0585171234783444, 1.0584589173853713, 1.0585109703694904, 1.0585722647110674, 1.0585694975442774, 1.0585613918282533, 1.05863132633195, 1.0585711705244334, 1.0585636075697284, 1.0586559470756192, 1.0586608367154284, 1.0586626390595844, 1.0586047033694042, 1.0585349008001894, 1.058547711041132, 1.0586169255989328, 1.1101839193766578, 1.1101782365722583, 1.1101790275456234, 1.1103213475861362, 1.1103567805522192, 1.1102564682182026, 1.1103536676704866, 1.1103390452542576, 1.1102594806570425, 1.1102263416849762, 1.110258027090615, 1.1102632499894618, 1.1102935249497354, 1.1102596350103866, 1.1102868501714735, 1.110372767946382, 1.1103164887023875, 1.1103321194703637, 1.1102984567028096, 1.110316621943563, 1.1102402923153172, 1.1102255936381615, 1.1101851766609223, 1.11038204842198, 1.1102997187498211, 1.1103563219705022, 1.1102203938557804, 1.1103195290093548, 1.1102705261685595, 1.1102306546522678, 22.56414665743874, 15.937220813825329, 17.950912831954987, 18.004977815008107, 14.642542356275428, 14.993107994245927, 14.845432382409768, 7.374110082952241, 10.710215086403823, 7.961687610817176, 7.105071679808904, 5.706528833173205, 6.541522822715587, 5.166564550004806, 3.813901994378811, 5.572282948089817, 5.160277823449274, 5.571983602757711, 4.355909930244017, 3.6786082563670535, 2.461799468147753, 4.715764643284865, 5.211657890411901, 4.17442678062026, 3.8601024882316652, 4.303514135880934, 5.394718097968745, 8.14259789571922, 2.462074015864437, 5.392672931522926, 7.763827722569217, 5.3185334365112515, 4.979606306369538, 4.715357615716328, 5.166564550004806, 3.813901994378811, 2.461942803359017, 2.4617675381562543, 2.462074015864437, 2.461799468147753, 2.462045235451206, 2.4620300357681515, 2.4620575081427094, 2.4624726775491226, 2.4625301791748804, 7.374110082952241, 1.786331626128884, 1.7860862450998418, 1.7862420331379518, 1.7863455814705511, 1.7862110613847892, 1.7863167824625399, 1.7865107722135, 1.7861690152057945, 1.786399333303107, 1.7864882201080092, 1.1101147089174472, 1.1103159261709645, 1.1103321194703637, 1.110354754432869, 1.1103337748673237, 1.1103601241253387, 1.1103869103174429, 1.1104245252450262, 22.56414665743874, 6.541522822715587, 2.410578377059999, 2.4100814363946963, 15.937220813825329, 5.706528833173205, 4.17442678062026, 2.6423621835512536, 14.642542356275428, 14.845432382409768, 5.762697722546733, 3.6581196803351217, 4.979606306369538, 5.211657890411901, 3.2664641342192864, 3.5003793794867137, 2.6424880941741113, 6.051511278043811, 3.5547914188224383, 3.555078795477086, 2.9305992140498205, 2.9311622694961748, 2.3068514347061946, 2.3067222213819187, 2.306783560025329, 2.306826408586847, 2.3067325862855066, 2.30703876176474, 2.3069865252678428, 2.307014061981615, 1.6827207775214286, 1.6825831981903032, 1.6827727106016745, 1.6825322818387116, 1.6827574476667604, 1.6827796806023447, 1.6826843824101312, 1.6827001470200504, 1.6828037330449557, 1.682831955138297, 1.6826392680136293, 7.763827722569217, 1.0586105515828887, 1.0585199450308538, 1.0585019158130065, 1.0586527776566945, 1.0586027728555643, 2.9827286556414996, 5.0864601466547334, 3.1630477275648796, 5.762697722546733, 3.6581196803351217, 5.3185334365112515, 14.642542356275428, 6.541522822715587, 17.950912831954987, 14.845432382409768, 3.3952378378920303, 3.215049456881805, 2.5389350890198585, 2.5392440927658226, 2.5390233462388982, 14.993107994245927, 10.710215086403823, 8.14259789571922, 5.571983602757711, 5.573404093615864, 5.572282948089817, 4.716295430199739, 4.716503211752251, 4.715764643284865, 4.7169663272763325, 4.715357615716328, 4.7159296318013375, 4.715728276526874, 3.8601024882316652, 3.861233639455667, 3.8610543645789415, 3.8599802412230373, 3.8601946522742887, 3.8596081319744906, 3.8599034696835397, 3.8601253010080714, 3.859762862487084, 3.8592549979280957, 3.859903251212257, 3.8599143675193335, 3.859808027485561, 17.950912831954987, 18.004977815008107, 3.0050470210221527, 3.0041904949986975, 7.961687610817176, 7.105071679808904, 14.845432382409768, 15.937220813825329, 22.56414665743874, 5.394718097968745, 5.392672931522926, 14.642542356275428, 5.160277823449274, 5.211657890411901], "Category": ["Default", "Default", "Default", "Default", "Default", "Default", "Default", "Default", "Default", "Default", "Default", "Default", "Default", "Default", "Default", "Default", "Default", "Default", "Default", "Default", "Default", "Default", "Default", "Default", "Default", "Default", "Default", "Default", "Default", "Default", "Topic1", "Topic1", "Topic1", "Topic1", "Topic1", "Topic1", "Topic1", "Topic1", "Topic1", "Topic1", "Topic1", "Topic1", "Topic1", "Topic1", "Topic1", "Topic1", "Topic1", "Topic1", "Topic1", "Topic1", "Topic1", "Topic1", "Topic1", "Topic1", "Topic1", "Topic1", "Topic1", "Topic1", "Topic1", "Topic1", "Topic1", "Topic1", "Topic1", "Topic1", "Topic1", "Topic1", "Topic1", "Topic1", "Topic1", "Topic1", "Topic1", "Topic1", "Topic1", "Topic1", "Topic1", "Topic1", "Topic1", "Topic1", "Topic1", "Topic1", "Topic1", "Topic1", "Topic1", "Topic1", "Topic1", "Topic1", "Topic1", "Topic1", "Topic1", "Topic1", "Topic1", "Topic1", "Topic1", "Topic1", "Topic1", "Topic1", "Topic1", "Topic1", "Topic1", "Topic1", "Topic1", "Topic1", "Topic1", "Topic1", "Topic1", "Topic1", "Topic1", "Topic1", "Topic1", "Topic1", "Topic1", "Topic1", "Topic1", "Topic1", "Topic1", "Topic1", "Topic1", "Topic1", "Topic1", "Topic1", "Topic1", "Topic1", "Topic1", "Topic1", "Topic2", "Topic2", "Topic2", "Topic2", "Topic2", "Topic2", "Topic2", "Topic2", "Topic2", "Topic2", "Topic2", "Topic2", "Topic2", "Topic2", "Topic2", "Topic2", "Topic2", "Topic2", "Topic2", "Topic2", "Topic2", "Topic2", "Topic2", "Topic2", "Topic2", "Topic2", "Topic2", "Topic2", "Topic2", "Topic2", "Topic2", "Topic2", "Topic2", "Topic2", "Topic2", "Topic2", "Topic2", "Topic2", "Topic2", "Topic2", "Topic2", "Topic2", "Topic2", "Topic2", "Topic2", "Topic2", "Topic2", "Topic2", "Topic2", "Topic2", "Topic2", "Topic2", "Topic2", "Topic2", "Topic2", "Topic2", "Topic2", "Topic2", "Topic2", "Topic2", "Topic2", "Topic2", "Topic2", "Topic2", "Topic2", "Topic2", "Topic2", "Topic2", "Topic2", "Topic2", "Topic2", "Topic2", "Topic2", "Topic2", "Topic2", "Topic2", "Topic2", "Topic2", "Topic2", "Topic2", "Topic2", "Topic2", "Topic2", "Topic2", "Topic2", "Topic2", "Topic2", "Topic2", "Topic2", "Topic2", "Topic2", "Topic2", "Topic2", "Topic2", "Topic2", "Topic3", "Topic3", "Topic3", "Topic3", "Topic3", "Topic3", "Topic3", "Topic3", "Topic3", "Topic3", "Topic3", "Topic3", "Topic3", "Topic3", "Topic3", "Topic3", "Topic3", "Topic3", "Topic3", "Topic3", "Topic3", "Topic3", "Topic3", "Topic3", "Topic3", "Topic3", "Topic3", "Topic3", "Topic3", "Topic3", "Topic3", "Topic3", "Topic3", "Topic3", "Topic3", "Topic3", "Topic3", "Topic3", "Topic3", "Topic3", "Topic3", "Topic3", "Topic3", "Topic3", "Topic3", "Topic3", "Topic3", "Topic4", "Topic4", "Topic4", "Topic4", "Topic4", "Topic4", "Topic4", "Topic4", "Topic4", "Topic4", "Topic4", "Topic4", "Topic4", "Topic4", "Topic4", "Topic4", "Topic4", "Topic4", "Topic4", "Topic4", "Topic4", "Topic4", "Topic4", "Topic4", "Topic4", "Topic4", "Topic4", "Topic4", "Topic4", "Topic4", "Topic4", "Topic4", "Topic4", "Topic4", "Topic4", "Topic4", "Topic4", "Topic4", "Topic4", "Topic4", "Topic4", "Topic4", "Topic4", "Topic4", "Topic4", "Topic5", "Topic5", "Topic5", "Topic5", "Topic5", "Topic5", "Topic5", "Topic5", "Topic5", "Topic5", "Topic5", "Topic5", "Topic5", "Topic5", "Topic5", "Topic5", "Topic5", "Topic5", "Topic5", "Topic5", "Topic5", "Topic5", "Topic5", "Topic5", "Topic5", "Topic5", "Topic5", "Topic5", "Topic5", "Topic5", "Topic5", "Topic5", "Topic5", "Topic5", "Topic5", "Topic5", "Topic5", "Topic5", "Topic5", "Topic5"], "logprob": [30.0, 29.0, 28.0, 27.0, 26.0, 25.0, 24.0, 23.0, 22.0, 21.0, 20.0, 19.0, 18.0, 17.0, 16.0, 15.0, 14.0, 13.0, 12.0, 11.0, 10.0, 9.0, 8.0, 7.0, 6.0, 5.0, 4.0, 3.0, 2.0, 1.0, -6.5659, -6.5663, -6.5663, -6.5664, -6.5664, -6.5664, -6.5664, -6.5664, -6.5664, -6.5664, -6.5665, -6.5665, -6.5666, -6.5666, -6.5666, -6.5666, -6.5666, -6.5666, -6.5666, -6.5666, -6.5667, -6.5666, -6.5666, -6.5666, -6.5667, -6.5667, -6.5667, -6.5667, -6.5668, -6.5668, -6.5668, -6.5627, -6.5634, -6.5634, -6.5635, -6.5635, -6.5635, -6.5635, -6.5636, -6.5636, -6.5636, -6.5636, -6.5637, -6.5637, -6.5638, -6.5638, -6.5638, -6.5639, -6.5639, -6.5639, -6.5639, -6.5639, -6.5639, -6.5639, -6.564, -6.564, -6.564, -6.564, -6.564, -6.564, -6.564, -6.4905, -6.5107, -6.515, -6.5323, -6.5249, -6.5273, -6.5362, -6.5299, -6.5301, -6.5429, -6.5437, -6.548, -6.5444, -6.5531, -6.5533, -6.5546, -6.5497, -6.5586, -6.5555, -6.5556, -6.5556, -6.5438, -6.547, -6.5502, -6.5508, -6.5523, -6.5531, -6.5533, -6.5537, -6.554, -6.554, -6.5542, -6.5549, -6.5685, -6.5684, -6.5684, -6.5686, -6.5685, -6.5685, -6.5686, -6.5687, -6.5687, -6.5686, -6.5687, -6.5687, -6.5687, -6.5688, -6.5687, -6.5688, -6.5688, -6.5688, -6.5688, -6.5688, -6.5688, -6.5688, -6.5688, -6.5688, -6.5688, -6.5688, -6.5688, -6.5689, -6.5689, -6.5689, -6.5689, -6.565, -6.5651, -6.5653, -6.5655, -6.5655, -6.5655, -6.5656, -6.5656, -6.5656, -6.5656, -6.5656, -6.5656, -6.5657, -6.5657, -6.5657, -6.5657, -6.5658, -6.5658, -6.5658, -6.5658, -6.5658, -6.5658, -6.5658, -6.5658, -6.5658, -6.5658, -6.5659, -6.5659, -6.5659, -6.5659, -6.4668, -6.4973, -6.4961, -6.4991, -6.5115, -6.5166, -6.5196, -6.5306, -6.5275, -6.5322, -6.5373, -6.5411, -6.54, -6.5453, -6.5493, -6.5465, -6.5476, -6.5469, -6.5496, -6.5518, -6.5562, -6.5497, -6.5487, -6.5511, -6.552, -6.5509, -6.5488, -6.5449, -6.5571, -6.5494, -6.5499, -6.5507, -6.5508, -6.5508, -4.1091, -4.4346, -4.92, -4.9201, -4.92, -4.9201, -4.92, -4.92, -4.9201, -4.9199, -4.92, -3.8639, -5.2945, -5.2947, -5.2946, -5.2946, -5.2947, -5.2947, -5.2946, -5.2948, -5.2947, -5.2946, -5.9007, -5.9005, -5.9005, -5.9005, -5.9005, -5.9005, -5.9005, -5.9005, -3.3618, -4.4344, -5.2945, -5.2947, -3.8639, -4.6481, -4.9201, -5.2945, -4.4336, -4.9192, -5.2933, -5.2936, -5.2937, -5.2942, -5.2942, -5.2944, -5.2946, -3.7178, -4.2883, -4.2886, -4.5017, -4.502, -4.7738, -4.7738, -4.7739, -4.7739, -4.774, -4.774, -4.774, -4.7742, -5.1483, -5.1486, -5.1485, -5.1487, -5.1486, -5.1486, -5.1487, -5.1487, -5.1486, -5.1486, -5.1487, -3.7177, -5.7543, -5.7544, -5.7544, -5.7543, -5.7544, -4.7736, -4.2881, -4.7736, -4.288, -4.7738, -4.5014, -4.2866, -4.773, -5.1426, -5.1433, -5.1476, -5.1477, -5.1481, -5.1481, -5.1482, -4.0642, -4.4079, -4.6899, -5.0847, -5.0845, -5.0847, -5.2605, -5.2605, -5.2606, -5.2604, -5.2608, -5.2607, -5.2608, -5.4737, -5.4734, -5.4736, -5.4739, -5.474, -5.4741, -5.474, -5.474, -5.4741, -5.4743, -5.4741, -5.4741, -5.4742, -3.9543, -3.9543, -5.7449, -5.7456, -4.8046, -4.9349, -4.3284, -4.4929, -4.2551, -5.2592, -5.2603, -4.6891, -5.4734, -5.4739], "loglift": [30.0, 29.0, 28.0, 27.0, 26.0, 25.0, 24.0, 23.0, 22.0, 21.0, 20.0, 19.0, 18.0, 17.0, 16.0, 15.0, 14.0, 13.0, 12.0, 11.0, 10.0, 9.0, 8.0, 7.0, 6.0, 5.0, 4.0, 3.0, 2.0, 1.0, 0.615, 0.6146, 0.6146, 0.6145, 0.6145, 0.6145, 0.6145, 0.6144, 0.6144, 0.6144, 0.6144, 0.6144, 0.6143, 0.6143, 0.6143, 0.6143, 0.6143, 0.6143, 0.6143, 0.6142, 0.6142, 0.6142, 0.6142, 0.6142, 0.6141, 0.6141, 0.6141, 0.6141, 0.6141, 0.614, 0.614, 0.5707, 0.5698, 0.5697, 0.5696, 0.5696, 0.5697, 0.5697, 0.5696, 0.5696, 0.5695, 0.5696, 0.5694, 0.5694, 0.5694, 0.5694, 0.5693, 0.5693, 0.5692, 0.5692, 0.5693, 0.5692, 0.5692, 0.5692, 0.5691, 0.5691, 0.5692, 0.5691, 0.5692, 0.569, 0.569, -2.3691, -2.0416, -2.1648, -1.2925, -2.1778, -1.9735, -1.1766, -1.9898, -1.9999, -0.9473, -1.0573, -0.6489, -1.0482, -0.2162, -0.2164, -0.2178, -0.7409, 0.0992, -0.2187, -0.2188, -0.2191, -1.6772, -1.3587, -1.4095, -0.9842, -0.9654, -1.39, -0.9421, -0.9213, -1.034, -0.6132, -0.8283, -1.278, 0.6125, 0.6125, 0.6124, 0.6124, 0.6123, 0.6123, 0.6123, 0.6122, 0.6122, 0.6122, 0.6122, 0.6122, 0.6122, 0.6121, 0.6121, 0.6121, 0.6121, 0.6121, 0.6121, 0.6121, 0.6121, 0.612, 0.612, 0.612, 0.612, 0.612, 0.612, 0.612, 0.612, 0.612, 0.6119, 0.5682, 0.5681, 0.568, 0.5676, 0.5676, 0.5677, 0.5675, 0.5675, 0.5676, 0.5676, 0.5676, 0.5675, 0.5675, 0.5675, 0.5675, 0.5674, 0.5674, 0.5673, 0.5674, 0.5673, 0.5674, 0.5674, 0.5674, 0.5672, 0.5673, 0.5673, 0.5674, 0.5673, 0.5673, 0.5673, -2.3454, -2.0282, -2.1459, -2.152, -1.9576, -1.9864, -1.9795, -1.2908, -1.661, -1.369, -1.2603, -1.045, -1.1804, -0.9497, -0.6502, -1.0266, -0.9508, -1.0269, -0.7833, -0.6166, -0.2193, -0.8628, -0.9618, -0.7423, -0.6649, -0.7726, -0.9964, -1.4042, -0.2203, -0.9966, -1.3616, -0.9841, -0.9184, -0.8639, 1.4865, 1.4645, 1.4169, 1.4168, 1.4168, 1.4168, 1.4168, 1.4168, 1.4167, 1.4167, 1.4166, 1.3759, 1.3631, 1.3631, 1.363, 1.363, 1.363, 1.363, 1.3629, 1.3629, 1.3629, 1.3629, 1.2326, 1.2326, 1.2326, 1.2326, 1.2326, 1.2326, 1.2326, 1.2326, 0.7596, 0.9253, 1.0635, 1.0635, 0.6053, 0.848, 0.8887, 0.9716, 0.1202, -0.3791, 0.1931, 0.6472, 0.3387, 0.2927, 0.7598, 0.6905, 0.9715, 1.7197, 1.6812, 1.6808, 1.6609, 1.6604, 1.6281, 1.6281, 1.628, 1.628, 1.6279, 1.6279, 1.6278, 1.6276, 1.5691, 1.5689, 1.5689, 1.5688, 1.5688, 1.5687, 1.5687, 1.5687, 1.5687, 1.5687, 1.5687, 1.4706, 1.4265, 1.4265, 1.4265, 1.4265, 1.4264, 1.3713, 1.3231, 1.3126, 1.1983, 1.167, 1.0652, 0.2672, 0.5866, -0.7925, -0.6032, 0.8678, 0.9222, 1.158, 1.1578, 1.1578, 0.466, 0.4587, 0.4507, 0.4354, 0.4353, 0.4352, 0.4263, 0.4262, 0.4262, 0.4262, 0.4262, 0.4261, 0.4261, 0.4134, 0.4133, 0.4132, 0.4132, 0.4131, 0.4131, 0.4131, 0.4131, 0.4131, 0.413, 0.413, 0.413, 0.4129, 0.3959, 0.3928, 0.3926, 0.3922, 0.3585, 0.3421, 0.2117, -0.0238, -0.1337, 0.2932, 0.2924, -0.1352, 0.1234, 0.113]}, "token.table": {"Topic": [3, 4, 5, 3, 4, 5, 3, 3, 4, 5, 5, 5, 3, 4, 5, 4, 3, 5, 3, 5, 4, 3, 4, 3, 3, 4, 4, 4, 4, 3, 4, 4, 3, 5, 3, 3, 4, 5, 4, 3, 4, 4, 5, 4, 3, 3, 3, 5, 4, 5, 3, 4, 3, 4, 5, 3, 5, 4, 4, 4, 4, 3, 5, 4, 5, 3, 5, 3, 5, 4, 5, 3, 4, 5, 4, 4, 5, 3, 5, 3, 5, 5, 3, 3, 4, 3, 5, 3, 5, 5, 4, 3, 3, 4, 5, 5, 3, 4, 3, 3, 3, 3, 3, 3, 4, 4, 3, 4, 5, 4, 4, 4, 5, 3, 5, 3, 4, 5, 3, 3, 4, 3, 3, 4, 3, 3, 5, 3, 5, 5, 3, 4, 4, 4, 4, 3, 4, 3, 3, 3, 3, 4, 3, 3, 3, 3, 5, 4, 3, 4, 4, 3, 4, 5, 4, 4, 5, 4, 5, 3, 4, 3, 3, 3, 4, 3, 5, 3, 4, 4, 3, 4, 3, 5, 5, 5, 4, 4, 4, 3, 4, 5, 4, 4, 5, 3, 3, 4, 5, 3, 3, 3, 3, 5, 3, 5, 3, 5, 4, 4, 3, 5, 5, 5, 3, 3, 4, 3, 4, 4, 4, 4, 3, 4, 3, 5, 3, 4, 3, 3, 4, 5, 3, 4, 5, 5, 3, 4, 3, 3, 3, 4, 3, 3, 3, 3, 4, 5, 3, 3, 4, 3, 5, 3, 4, 4, 3, 3, 3, 4, 3, 4, 4, 4, 5, 4, 3, 4, 3, 3, 5, 3, 4, 4, 3, 4, 5], "Freq": [0.19378801572578355, 0.19378801572578355, 0.7751520629031342, 0.19660038045470202, 0.589801141364106, 0.19660038045470202, 0.9007059164773962, 0.9006577081060447, 0.9446159159722757, 1.0362953455745219, 0.8971177965953199, 1.0362357923861696, 0.5598345473055889, 0.5943044471917673, 0.848189076661885, 0.9446629067495733, 0.9006441047891552, 1.0362924197644043, 0.9006439967092825, 1.035938348595734, 0.9446413949044511, 0.9007178412479603, 0.9446695960032463, 0.5597852514594088, 0.8124138565619201, 0.9446571841986461, 0.9447132026449468, 0.9446710889741771, 0.9446418185011017, 0.9006334397669494, 1.0234847900507595, 0.5942885133144736, 0.4431809521457481, 0.5318171425748976, 0.812191752718484, 0.27317660435420904, 0.20488245326565677, 0.5463532087084181, 0.8439313722079878, 0.9006326278314368, 0.9446230516314058, 0.9445895846138713, 1.0362954042290422, 0.9447055747914342, 0.9006117948023591, 0.81232326368458, 0.9005841093080434, 0.8973465028729406, 1.0236814319806884, 0.9983204851748256, 0.41483820211630074, 0.41483820211630074, 0.9006314259169653, 0.8669825762987308, 1.0362747345910241, 0.19187752170758188, 0.7675100868303275, 0.9446616812903375, 0.9446871219469876, 0.9446237798521492, 0.9447019642376075, 0.9006684371713787, 0.848291969768733, 0.3938659181657316, 0.3938659181657316, 0.8123377744967281, 0.9824874201642466, 0.18543679779919334, 0.7417471911967733, 0.6323015560500981, 0.31615077802504904, 0.9006872919638578, 0.3938179881362919, 0.3938179881362919, 0.594236398320484, 0.055707473450590676, 0.8913195752094508, 0.2718419386650285, 0.8155258159950856, 0.37647718319840806, 0.6274619719973468, 0.9336880650225773, 0.900610255120683, 1.0487946480783914, 0.5942573193039543, 0.9005564784147216, 0.8482252931981894, 0.28568331931684426, 0.5713666386336885, 0.8480026615559236, 0.9446396722186545, 0.559806468951723, 0.055540196176551065, 0.055540196176551065, 0.888643138824817, 0.8481232906630273, 0.9006943464932062, 0.594342236873563, 0.9006217262981804, 0.9007516525383258, 0.900713735303235, 0.9006813892924882, 0.9007172343635018, 0.5597573993180549, 0.8670311411843223, 0.9446717370237616, 0.9006915289957041, 0.7728146752352809, 0.25760489174509366, 0.9446905317252563, 0.8669214604969054, 0.9446344536286255, 1.0004596782572845, 0.2205028083663312, 0.8820112334653248, 0.3061414296652024, 0.3061414296652024, 0.3061414296652024, 0.5598111207472635, 0.5598833778287678, 0.9445879764759672, 0.9005695818124012, 0.900641638621106, 0.5942627093325644, 0.9006593680167978, 0.18536649771867164, 0.7414659908746866, 0.9006401634752161, 1.036469474587055, 1.0362171756399234, 0.9006114228461459, 0.9446916348381638, 0.5942829456400377, 0.9447153118790331, 0.944704706921319, 0.9006474667029263, 0.86702724532997, 0.9006927936252892, 0.9677610628121057, 0.9006627324475043, 0.9007020794647683, 0.9446756027579352, 0.9006300831653007, 0.9007506324374429, 0.5598574331359031, 0.47910769672257336, 0.47910769672257336, 0.5942463641856476, 0.4149237386334655, 0.4149237386334655, 0.9446233033794056, 0.3110372059314679, 0.3110372059314679, 0.3110372059314679, 0.9446944900977409, 0.9446176119646996, 1.036241916424458, 0.294530176601961, 0.589060353203922, 0.900608710879029, 0.8670080863494795, 0.9006139477145082, 0.9007562633253916, 0.9006681470158449, 0.9447483832832972, 0.5257136321752015, 0.5257136321752015, 0.9006587318599392, 0.9447314029960232, 0.9447483240666155, 0.900625808192676, 0.944668619551397, 0.9005869852285229, 1.036333096749512, 0.9986051167508606, 0.8480859273101058, 0.9914878654806932, 0.9447233217157247, 0.9447697814008901, 0.18802175673750404, 0.5640652702125122, 0.3760435134750081, 0.9446287659100395, 0.3938522272673539, 0.3938522272673539, 0.9007234332397758, 0.20081908859358524, 0.20081908859358524, 0.6024572657807556, 0.900722059812839, 0.812424393855605, 0.5598020956151062, 0.37843122253027295, 0.37843122253027295, 0.1407445336324736, 0.8444672017948416, 0.37844925507374266, 0.37844925507374266, 0.9446783225986438, 0.9446503836704873, 0.1256015117500147, 0.879210582250103, 1.0363746430272154, 0.8482187519039788, 0.9006325083700975, 0.9006805440795297, 0.8438631525739234, 0.2733644843211881, 0.5467289686423762, 0.5942548579158347, 0.9446719267199621, 0.944617337806668, 0.900644561092265, 0.8669919819520326, 0.2295731583099975, 0.6887194749299925, 0.5598442544772585, 0.594324251588597, 0.9005713345431453, 0.1735298376118999, 0.5205895128356998, 0.1735298376118999, 0.23236823870576154, 0.23236823870576154, 0.6971047161172846, 0.8972982970496867, 0.9005909285197383, 0.9446423222329167, 0.5597503331933412, 0.9008078101903289, 0.900662467312916, 0.9446330959170794, 0.9006173528020274, 0.8123327594480492, 0.9005984556425003, 0.6114784138809253, 0.30573920694046264, 0.15286960347023132, 0.9007556215602393, 0.9006902245803478, 0.8669318082678436, 0.900601759416556, 1.0363209702441512, 0.9005650609141314, 0.9445957939810607, 0.5942756596094063, 0.9006496494180194, 0.9006903497984167, 0.9006130662364441, 0.9446763452371275, 0.3352634836925616, 0.6705269673851232, 0.9445967753596026, 0.9446142777817328, 1.035986448855975, 0.8669121790004626, 0.8123665575297878, 0.9445939474126155, 0.8123287101887114, 0.8136575034146882, 0.13560958390244804, 0.8121727875311318, 0.9447178300847379, 0.9446520865384113, 0.13472157283675912, 0.06736078641837956, 0.7409686506021751], "Term": ["%", "%", "%", "-", "-", "-", "1956", "2000", "2019", "2030", "Abdeslam Bouchouareb", "Algeria", "Brazil", "Centre", "Chakib Khelil", "Chambers", "Counterfeiting", "Dubai", "EU", "Geneva", "Genevan", "Hong Kong", "Houses of Parliament", "India", "Jean-Daniel Pasche", "Le Centre", "Lisa Mazzone", "Lukas Golder", "Marianne Binder-Keller", "More\n\nImmigration", "PLR", "Parliament", "Swiss", "Swiss", "Swissness", "Switzerland", "Switzerland", "Switzerland", "UDC", "Vaud", "Vert-e-s", "Vert\u2019lib\u00e9raux", "Wertli", "Zurich", "ability", "actor", "ad", "agreement", "alliance", "amount", "analysis", "analysis", "announcement", "area", "article", "authority", "authority", "backguard", "blockage", "bourgeois", "brake", "brand", "c", "campaign", "campaign", "capital", "carbon", "case", "case", "centre", "centre", "challenge", "citizen", "citizen", "city", "climate", "climate", "commitment", "commitment", "company", "company", "compensation", "competition", "component", "compromise", "condition", "conference", "consumer", "consumer", "corruption", "cost", "counterfeiting", "country", "country", "country", "credit", "debate", "defeat", "destruction", "detection", "dialogue", "director", "discrimination", "doctor", "e", "ecologist", "economy", "election", "election", "elective", "electorate", "element", "emission", "energy", "energy", "example", "example", "example", "export", "fabric", "factor", "fh", "fight", "force", "framework", "franc", "franc", "frustration", "fuel", "fund", "growth", "handicap", "health", "hope", "house", "how", "idea", "implementation", "industry", "input", "interest", "introduction", "issue", "know", "label", "law", "law", "left", "legislation", "legislation", "lesson", "level", "level", "level", "liberal", "lifestyle", "limit", "loss", "loss", "luxury", "majority", "mandate", "manoeuvre", "margin", "mark", "market", "market", "material", "minority", "moderator", "movement", "non", "object", "objective", "official", "oil", "party", "personality", "polarization", "policy", "policy", "policy", "positioning", "possibility", "possibility", "precision", "president", "president", "president", "pride", "process", "product", "production", "production", "project", "project", "property", "property", "recent years", "recipe", "reduction", "reduction", "report", "request", "retortion", "reverence", "right", "risk", "risk", "role", "rotation", "s", "scourge", "seat", "sector", "sector", "segment", "share", "shortage", "solution", "solution", "solution", "standard", "standard", "standard", "state", "statistic", "style", "subcontractor", "supply", "suppression", "symbol", "taxis", "technology", "tension", "term", "term", "term", "text", "the Brand Division", "the Council of States", "the Federal Office of Intellectual Property", "the Federal Office of Justice", "the Federation of Swiss watch industry", "the Greens\u2019 Liberals", "the National Council", "the University of Neuch\u00e2tel", "the end of December 2023", "the last two years", "the next 20 years", "theme", "theme", "thing", "this election Sunday", "today", "training", "transfer", "trend", "volume", "watch", "watch", "watchmaking", "wave", "weakness", "year", "year", "year"]}, "R": 30, "lambda.step": 0.01, "plot.opts": {"xlab": "PC1", "ylab": "PC2"}, "topic.order": [1, 2, 3, 4, 5]}